<?xml version="1.0" encoding="utf-8" standalone="yes" ?>
<T3locallang>
	<meta type="array">
		<type>database</type>
		<description>Language labels for extension &quot;realurl_force404lang&quot;</description>
	</meta>
	<data type="array">
		<languageKey index="default" type="array">
			<label index="extmng.pageNotFound_handling">How TYPO3 should handle requests for non-existing/accessible pages: This should be the same as $GLOBALS['TYPO3_CONF_VARS']['FE']['pageNotFound_handling']. Default: ''</label>
			<label index="extmng.languageParam">Language parameter: This should be the same as config.linkVars. Default: 'L'</label>
		</languageKey>
		<languageKey index="de" type="array">
			<label index="extmng.pageNotFound_handling">TYPO3-Handler für nicht existierende/zugriffsgeschützte Seiten: Sollte $GLOBALS['TYPO3_CONF_VARS']['FE']['pageNotFound_handling'] entsprechen. Standard: ''</label>
			<label index="extmng.languageParam">Sprachparameter: Sollte config.linkVars entsprechen. Standard: 'L'</label>
		</languageKey>
	</data>
</T3locallang>
