<?xml version="1.0" encoding="UTF-8" ?>
<RESULT>
<SESSION><SESSIONVAR name="LNG">DU</SESSIONVAR>
<SESSIONVAR name="DB">1</SESSIONVAR>
<SESSIONVAR name="SID">92294f0c-4</SESSIONVAR>


<SESSIONVAR name="TITLE">G%26ouml%3Bttinger+Universit%26auml%3Btskatalog+(GUK)</SESSIONVAR>
</SESSION>
<SCANLIST>

    <SCANLINE hits="1" mnemonic="LKL" description="vao ly">vao ly</SCANLINE>

    <SCANLINE hits="2" mnemonic="LKL" description="vao rr">vao rr</SCANLINE>

    <SCANLINE hits="4" mnemonic="LKL" description="vao ru">vao ru</SCANLINE>

    <SCANLINE hits="1" mnemonic="LKL" description="vao vc">vao vc</SCANLINE>

    <SCANLINE hits="1" mnemonic="LKL" description="vao16 bel">vao16 bel</SCANLINE>

    <SCANLINE hits="1" mnemonic="LKL" description="vao16 belg">vao16 belg</SCANLINE>

    <SCANLINE hits="2" mnemonic="LKL" description="vao16 frank">vao16 frank</SCANLINE>

    <SCANLINE hits="2" mnemonic="LKL" description="vao16 gb">vao16 gb</SCANLINE>

    <SCANLINE hits="1" mnemonic="LKL" description="vao16 it">vao16 it</SCANLINE>

    <SCANLINE hits="1" mnemonic="LKL" description="vao16 jug">vao16 jug</SCANLINE>

    <SCANLINE hits="1" mnemonic="LKL" description="vao16 schwd">vao16 schwd</SCANLINE>

    <SCANLINE hits="3" mnemonic="LKL" description="vao16 span">vao16 span</SCANLINE>

    <SCANLINE hits="2" mnemonic="LKL" description="vao16 tsche">vao16 tsche</SCANLINE>

    <SCANLINE hits="1" mnemonic="LKL" description="vao2 brd">vao2 brd</SCANLINE>

    <SCANLINE hits="1" mnemonic="LKL" description="vao21">vao21</SCANLINE>

    <SCANLINE hits="1" mnemonic="LKL" description="vao66 kan">vao66 kan</SCANLINE>

    <SCANLINE hits="1" mnemonic="LKL" description="vaoz">vaoz</SCANLINE>

    <SCANLINE hits="3" mnemonic="LKL" description="vap">vap</SCANLINE>

    <SCANLINE hits="56" mnemonic="LKL" description="vap 000">vap 000</SCANLINE>

    <SCANLINE hits="5" mnemonic="LKL" description="vap ab">vap ab</SCANLINE>

    <SCANLINE hits="1" mnemonic="LKL" description="vap c">vap c</SCANLINE>

    <SCANLINE hits="1" mnemonic="LKL" description="vap go">vap go</SCANLINE>

    <SCANLINE hits="1" mnemonic="LKL" description="vap lg">vap lg</SCANLINE>

    <SCANLINE hits="1" mnemonic="LKL" description="vap odd">vap odd</SCANLINE>

    <SCANLINE hits="1" mnemonic="LKL" description="vap rr">vap rr</SCANLINE>

    <SCANLINE hits="10" mnemonic="LKL" description="vaq">vaq</SCANLINE>

    <SCANLINE hits="57" mnemonic="LKL" description="vaq 000">vaq 000</SCANLINE>

    <SCANLINE hits="83" mnemonic="LKL" description="vaq 100">vaq 100</SCANLINE>

    <SCANLINE hits="1" mnemonic="LKL" description="vaq 16 schw var 16 schw tw 16 schw">vaq 16 schw var 16 schw tw 16 schw</SCANLINE>

    <SCANLINE hits="2" mnemonic="LKL" description="vaq 200">vaq 200</SCANLINE>

    <SCANLINE hits="6" mnemonic="LKL" description="vaq 300">vaq 300</SCANLINE>

    <SCANLINE hits="41" mnemonic="LKL" description="vaq 400">vaq 400</SCANLINE>

    <SCANLINE hits="65" mnemonic="LKL" description="vaq 500">vaq 500</SCANLINE>

    <SCANLINE hits="14" mnemonic="LKL" description="vaq 600">vaq 600</SCANLINE>

    <SCANLINE hits="6" mnemonic="LKL" description="vaq 700">vaq 700</SCANLINE>

    <SCANLINE hits="5" mnemonic="LKL" description="vaq 800">vaq 800</SCANLINE>

    <SCANLINE hits="7" mnemonic="LKL" description="vaq 900">vaq 900</SCANLINE>

    <SCANLINE hits="6" mnemonic="LKL" description="vaq 910">vaq 910</SCANLINE>

    <SCANLINE hits="61" mnemonic="LKL" description="vaq 911">vaq 911</SCANLINE>

    <SCANLINE hits="9" mnemonic="LKL" description="vaq 912">vaq 912</SCANLINE>

    <SCANLINE hits="6" mnemonic="LKL" description="vaq 913">vaq 913</SCANLINE>

    <SCANLINE hits="2" mnemonic="LKL" description="vaq 914">vaq 914</SCANLINE>

    <SCANLINE hits="2" mnemonic="LKL" description="vaq 915">vaq 915</SCANLINE>

    <SCANLINE hits="3" mnemonic="LKL" description="vaq 916">vaq 916</SCANLINE>

    <SCANLINE hits="23" mnemonic="LKL" description="vaq 917">vaq 917</SCANLINE>

    <SCANLINE hits="21" mnemonic="LKL" description="vaq 918">vaq 918</SCANLINE>

    <SCANLINE hits="52" mnemonic="LKL" description="vaq 919">vaq 919</SCANLINE>

    <SCANLINE hits="3" mnemonic="LKL" description="vaq 920">vaq 920</SCANLINE>

    <SCANLINE hits="2" mnemonic="LKL" description="vaq 921">vaq 921</SCANLINE>

    <SCANLINE hits="10" mnemonic="LKL" description="vaq 922">vaq 922</SCANLINE>

    <SCANLINE hits="2" mnemonic="LKL" description="vaq 923">vaq 923</SCANLINE>

    <SCANLINE hits="4" mnemonic="LKL" description="vaq 924">vaq 924</SCANLINE>

    <SCANLINE hits="34" mnemonic="LKL" description="vaq 933">vaq 933</SCANLINE>

    <SCANLINE hits="4" mnemonic="LKL" description="vaq 950">vaq 950</SCANLINE>

    <SCANLINE hits="48" mnemonic="LKL" description="vaq 990">vaq 990</SCANLINE>

    <SCANLINE hits="1" mnemonic="LKL" description="vaq ab">vaq ab</SCANLINE>

    <SCANLINE hits="1" mnemonic="LKL" description="vaq c">vaq c</SCANLINE>

    <SCANLINE hits="1" mnemonic="LKL" description="vaq ca">vaq ca</SCANLINE>

    <SCANLINE hits="1" mnemonic="LKL" description="vaq go">vaq go</SCANLINE>

    <SCANLINE hits="1" mnemonic="LKL" description="vaq gs">vaq gs</SCANLINE>

    <SCANLINE hits="1" mnemonic="LKL" description="vaq hj">vaq hj</SCANLINE>

    <SCANLINE hits="2" mnemonic="LKL" description="vaq hx">vaq hx</SCANLINE>

    <SCANLINE hits="1" mnemonic="LKL" description="vaq j">vaq j</SCANLINE>

    <SCANLINE hits="1" mnemonic="LKL" description="vaq jf">vaq jf</SCANLINE>

    <SCANLINE hits="4" mnemonic="LKL" description="vaq jk">vaq jk</SCANLINE>

    <SCANLINE hits="1" mnemonic="LKL" description="vaq kk">vaq kk</SCANLINE>

    <SCANLINE hits="3" mnemonic="LKL" description="vaq lg">vaq lg</SCANLINE>

    <SCANLINE hits="1" mnemonic="LKL" description="vaq os">vaq os</SCANLINE>

    <SCANLINE hits="2" mnemonic="LKL" description="vaq ou">vaq ou</SCANLINE>

    <SCANLINE hits="5" mnemonic="LKL" description="vaq ru">vaq ru</SCANLINE>

    <SCANLINE hits="1" mnemonic="LKL" description="vaq66 kan var66 kan">vaq66 kan var66 kan</SCANLINE>

    <SCANLINE hits="2" mnemonic="LKL" description="vaq66 usa">vaq66 usa</SCANLINE>

    <SCANLINE hits="20" mnemonic="LKL" description="var">var</SCANLINE>

    <SCANLINE hits="71" mnemonic="LKL" description="var 000">var 000</SCANLINE>

    <SCANLINE hits="19" mnemonic="LKL" description="var 100">var 100</SCANLINE>

    <SCANLINE hits="1" mnemonic="LKL" description="var 140">var 140</SCANLINE>

    <SCANLINE hits="1" mnemonic="LKL" description="var 16 no">var 16 no</SCANLINE>

    <SCANLINE hits="41" mnemonic="LKL" description="var 200">var 200</SCANLINE>

    <SCANLINE hits="14" mnemonic="LKL" description="var 300">var 300</SCANLINE>

    <SCANLINE hits="25" mnemonic="LKL" description="var 310">var 310</SCANLINE>

    <SCANLINE hits="48" mnemonic="LKL" description="var 320">var 320</SCANLINE>

    <SCANLINE hits="7" mnemonic="LKL" description="var 330">var 330</SCANLINE>

    <SCANLINE hits="74" mnemonic="LKL" description="var 400">var 400</SCANLINE>

    <SCANLINE hits="94" mnemonic="LKL" description="var 500">var 500</SCANLINE>

    <SCANLINE hits="17" mnemonic="LKL" description="var 600">var 600</SCANLINE>

    <SCANLINE hits="1" mnemonic="LKL" description="var 66 kan">var 66 kan</SCANLINE>

    <SCANLINE hits="14" mnemonic="LKL" description="var 700">var 700</SCANLINE>

    <SCANLINE hits="72" mnemonic="LKL" description="var 800">var 800</SCANLINE>

    <SCANLINE hits="13" mnemonic="LKL" description="var 900">var 900</SCANLINE>

    <SCANLINE hits="27" mnemonic="LKL" description="var 910">var 910</SCANLINE>

    <SCANLINE hits="72" mnemonic="LKL" description="var 911">var 911</SCANLINE>

    <SCANLINE hits="54" mnemonic="LKL" description="var 912">var 912</SCANLINE>

    <SCANLINE hits="21" mnemonic="LKL" description="var 913">var 913</SCANLINE>

    <SCANLINE hits="51" mnemonic="LKL" description="var 914">var 914</SCANLINE>

    <SCANLINE hits="16" mnemonic="LKL" description="var 915">var 915</SCANLINE>

    <SCANLINE hits="7" mnemonic="LKL" description="var 916">var 916</SCANLINE>

    <SCANLINE hits="24" mnemonic="LKL" description="var 920">var 920</SCANLINE>

    <SCANLINE hits="6" mnemonic="LKL" description="var 930">var 930</SCANLINE>

    <SCANLINE hits="47" mnemonic="LKL" description="var 940">var 940</SCANLINE>

    <SCANLINE hits="7" mnemonic="LKL" description="var 950">var 950</SCANLINE>

    <SCANLINE hits="6" mnemonic="LKL" description="var 960">var 960</SCANLINE>

    <SCANLINE hits="24" mnemonic="LKL" description="var 970">var 970</SCANLINE>

    <SCANLINE hits="19" mnemonic="LKL" description="var 980">var 980</SCANLINE>

    <SCANLINE hits="2" mnemonic="LKL" description="var 990">var 990</SCANLINE>

    <SCANLINE hits="1" mnemonic="LKL" description="var ab">var ab</SCANLINE>

    <SCANLINE hits="1" mnemonic="LKL" description="var c">var c</SCANLINE>

    <SCANLINE hits="1" mnemonic="LKL" description="var ca">var ca</SCANLINE>

    <SCANLINE hits="1" mnemonic="LKL" description="var go">var go</SCANLINE>

    <SCANLINE hits="2" mnemonic="LKL" description="var gs">var gs</SCANLINE>

    <SCANLINE hits="1" mnemonic="LKL" description="var js">var js</SCANLINE>

    <SCANLINE hits="1" mnemonic="LKL" description="var ld">var ld</SCANLINE>

    <SCANLINE hits="2" mnemonic="LKL" description="var lg">var lg</SCANLINE>

    <SCANLINE hits="1" mnemonic="LKL" description="var ng">var ng</SCANLINE>

    <SCANLINE hits="3" mnemonic="LKL" description="var ru">var ru</SCANLINE>

    <SCANLINE hits="1" mnemonic="LKL" description="var16 ndl vas16 ndl vbp16 ndl">var16 ndl vas16 ndl vbp16 ndl</SCANLINE>

    <SCANLINE hits="2" mnemonic="LKL" description="var2 d">var2 d</SCANLINE>

    <SCANLINE hits="1" mnemonic="LKL" description="var56 usa">var56 usa</SCANLINE>

    <SCANLINE hits="27" mnemonic="LKL" description="vas 000">vas 000</SCANLINE>

    <SCANLINE hits="5" mnemonic="LKL" description="vas ab">vas ab</SCANLINE>

    <SCANLINE hits="1" mnemonic="LKL" description="vas hn">vas hn</SCANLINE>

    <SCANLINE hits="1" mnemonic="LKL" description="vas js">vas js</SCANLINE>

    <SCANLINE hits="12" mnemonic="LKL" description="vas lg">vas lg</SCANLINE>

    <SCANLINE hits="1" mnemonic="LKL" description="vas os">vas os</SCANLINE>

    <SCANLINE hits="1" mnemonic="LKL" description="vas rr">vas rr</SCANLINE>

    <SCANLINE hits="1" mnemonic="LKL" description="vas ru">vas ru</SCANLINE>

    <SCANLINE hits="1" mnemonic="LKL" description="vas16 udssr">vas16 udssr</SCANLINE>

    <SCANLINE hits="15" mnemonic="LKL" description="vat">vat</SCANLINE>

    <SCANLINE hits="59" mnemonic="LKL" description="vat 000">vat 000</SCANLINE>

    <SCANLINE hits="80" mnemonic="LKL" description="vat 100">vat 100</SCANLINE>

    <SCANLINE hits="102" mnemonic="LKL" description="vat 110">vat 110</SCANLINE>

    <SCANLINE hits="10" mnemonic="LKL" description="vat 120">vat 120</SCANLINE>

    <SCANLINE hits="10" mnemonic="LKL" description="vat 130">vat 130</SCANLINE>

    <SCANLINE hits="16" mnemonic="LKL" description="vat 140">vat 140</SCANLINE>

    <SCANLINE hits="15" mnemonic="LKL" description="vat 150">vat 150</SCANLINE>

    <SCANLINE hits="1" mnemonic="LKL" description="vat 16 gri">vat 16 gri</SCANLINE>

    <SCANLINE hits="2" mnemonic="LKL" description="vat 16 it">vat 16 it</SCANLINE>

    <SCANLINE hits="4" mnemonic="LKL" description="vat 160">vat 160</SCANLINE>

    <SCANLINE hits="16" mnemonic="LKL" description="vat 200">vat 200</SCANLINE>

    <SCANLINE hits="39" mnemonic="LKL" description="vat 210">vat 210</SCANLINE>

    <SCANLINE hits="93" mnemonic="LKL" description="vat 220">vat 220</SCANLINE>

    <SCANLINE hits="38" mnemonic="LKL" description="vat 230">vat 230</SCANLINE>

    <SCANLINE hits="128" mnemonic="LKL" description="vat 240">vat 240</SCANLINE>

    <SCANLINE hits="23" mnemonic="LKL" description="vat 250">vat 250</SCANLINE>

    <SCANLINE hits="38" mnemonic="LKL" description="vat 260">vat 260</SCANLINE>

    <SCANLINE hits="20" mnemonic="LKL" description="vat 270">vat 270</SCANLINE>

    <SCANLINE hits="36" mnemonic="LKL" description="vat 280">vat 280</SCANLINE>

    <SCANLINE hits="187" mnemonic="LKL" description="vat 300">vat 300</SCANLINE>

    <SCANLINE hits="1" mnemonic="LKL" description="vat a">vat a</SCANLINE>

    <SCANLINE hits="5" mnemonic="LKL" description="vat ab">vat ab</SCANLINE>

    <SCANLINE hits="2" mnemonic="LKL" description="vat go">vat go</SCANLINE>

    <SCANLINE hits="1" mnemonic="LKL" description="vat gs">vat gs</SCANLINE>

    <SCANLINE hits="3" mnemonic="LKL" description="vat gx">vat gx</SCANLINE>

    <SCANLINE hits="5" mnemonic="LKL" description="vat jf">vat jf</SCANLINE>

    <SCANLINE hits="3" mnemonic="LKL" description="vat jk">vat jk</SCANLINE>

    <SCANLINE hits="1" mnemonic="LKL" description="vat k (fh)">vat k (fh)</SCANLINE>

    <SCANLINE hits="1" mnemonic="LKL" description="vat kf">vat kf</SCANLINE>

    <SCANLINE hits="2" mnemonic="LKL" description="vat kk">vat kk</SCANLINE>

    <SCANLINE hits="2" mnemonic="LKL" description="vat kq">vat kq</SCANLINE>

    <SCANLINE hits="1" mnemonic="LKL" description="vat ks">vat ks</SCANLINE>

    <SCANLINE hits="2" mnemonic="LKL" description="vat ku">vat ku</SCANLINE>

    <SCANLINE hits="1" mnemonic="LKL" description="vat ld">vat ld</SCANLINE>

    <SCANLINE hits="18" mnemonic="LKL" description="vat lg">vat lg</SCANLINE>

    <SCANLINE hits="1" mnemonic="LKL" description="vat lw">vat lw</SCANLINE>

    <SCANLINE hits="3" mnemonic="LKL" description="vat ru">vat ru</SCANLINE>

    <SCANLINE hits="1" mnemonic="LKL" description="vat uc">vat uc</SCANLINE>

    <SCANLINE hits="1" mnemonic="LKL" description="vat vj va jk">vat vj va jk</SCANLINE>

    <SCANLINE hits="1" mnemonic="LKL" description="vat16 finn">vat16 finn</SCANLINE>

    <SCANLINE hits="1" mnemonic="LKL" description="vat16 frank ve 16 frank">vat16 frank ve 16 frank</SCANLINE>

    <SCANLINE hits="1" mnemonic="LKL" description="vat16 oest">vat16 oest</SCANLINE>

    <SCANLINE hits="1" mnemonic="LKL" description="vat16 span ve 16 span">vat16 span ve 16 span</SCANLINE>

    <SCANLINE hits="1" mnemonic="LKL" description="vat16 udssr">vat16 udssr</SCANLINE>

    <SCANLINE hits="36" mnemonic="LKL" description="vau">vau</SCANLINE>

    <SCANLINE hits="64" mnemonic="LKL" description="vau 000">vau 000</SCANLINE>

    <SCANLINE hits="1" mnemonic="LKL" description="vau 71">vau 71</SCANLINE>

    <SCANLINE hits="1" mnemonic="LKL" description="vau a">vau a</SCANLINE>

    <SCANLINE hits="1" mnemonic="LKL" description="vau c">vau c</SCANLINE>

    <SCANLINE hits="1" mnemonic="LKL" description="vau hs">vau hs</SCANLINE>

    <SCANLINE hits="1" mnemonic="LKL" description="vau rr">vau rr</SCANLINE>

    <SCANLINE hits="1" mnemonic="LKL" description="vau ru">vau ru</SCANLINE>

    <SCANLINE hits="1" mnemonic="LKL" description="vau2 d vat2 d">vau2 d vat2 d</SCANLINE>

    <SCANLINE hits="2" mnemonic="LKL" description="vau56 sau">vau56 sau</SCANLINE>

    <SCANLINE hits="1" mnemonic="LKL" description="vau66 usa vbz66 usa">vau66 usa vbz66 usa</SCANLINE>

    <SCANLINE hits="1" mnemonic="LKL" description="vau94">vau94</SCANLINE>

    <SCANLINE hits="2" mnemonic="LKL" description="vav">vav</SCANLINE>

    <SCANLINE hits="1" mnemonic="LKL" description="vav ab">vav ab</SCANLINE>

    <SCANLINE hits="1" mnemonic="LKL" description="vav ab a">vav ab a</SCANLINE>

    <SCANLINE hits="1" mnemonic="LKL" description="vav cc">vav cc</SCANLINE>

    <SCANLINE hits="1" mnemonic="LKL" description="vav jf a">vav jf a</SCANLINE>

    <SCANLINE hits="1" mnemonic="LKL" description="vav lg">vav lg</SCANLINE>

    <SCANLINE hits="3" mnemonic="LKL" description="vav ru">vav ru</SCANLINE>

    <SCANLINE hits="3" mnemonic="LKL" description="vaw">vaw</SCANLINE>

    <SCANLINE hits="2" mnemonic="LKL" description="vaw rr">vaw rr</SCANLINE>

    <SCANLINE hits="1" mnemonic="LKL" description="vaw66 kan">vaw66 kan</SCANLINE>

    <SCANLINE hits="2" mnemonic="LKL" description="vax">vax</SCANLINE>

    <SCANLINE hits="1" mnemonic="LKL" description="vax 00">vax 00</SCANLINE>

    <SCANLINE hits="59" mnemonic="LKL" description="vax 000">vax 000</SCANLINE>

    <SCANLINE hits="54" mnemonic="LKL" description="vb">vb</SCANLINE>

    <SCANLINE hits="28" mnemonic="LKL" description="vb 000">vb 000</SCANLINE>

    <SCANLINE hits="1" mnemonic="LKL" description="vb 16 su p 16 su">vb 16 su p 16 su</SCANLINE>

    <SCANLINE hits="3" mnemonic="LKL" description="vb 2 d">vb 2 d</SCANLINE>

    <SCANLINE hits="1" mnemonic="LKL" description="vb 2 d vq 2 d">vb 2 d vq 2 d</SCANLINE>

    <SCANLINE hits="1" mnemonic="LKL" description="vb 46 ind">vb 46 ind</SCANLINE>

    <SCANLINE hits="2" mnemonic="LKL" description="vb a">vb a</SCANLINE>

    <SCANLINE hits="3" mnemonic="LKL" description="vb j">vb j</SCANLINE>

    <SCANLINE hits="1" mnemonic="LKL" description="vb jf">vb jf</SCANLINE>

    <SCANLINE hits="1" mnemonic="LKL" description="vba">vba</SCANLINE>

    <SCANLINE hits="57" mnemonic="LKL" description="vba 000">vba 000</SCANLINE>

    <SCANLINE hits="42" mnemonic="LKL" description="vbb 000">vbb 000</SCANLINE>

    <SCANLINE hits="37" mnemonic="LKL" description="vbc 000">vbc 000</SCANLINE>

    <SCANLINE hits="9" mnemonic="LKL" description="vbd">vbd</SCANLINE>

    <SCANLINE hits="184" mnemonic="LKL" description="vbd 000">vbd 000</SCANLINE>

    <SCANLINE hits="1" mnemonic="LKL" description="vbd 66usa p">vbd 66usa p</SCANLINE>

    <SCANLINE hits="11" mnemonic="LKL" description="vbd 800">vbd 800</SCANLINE>

    <SCANLINE hits="1" mnemonic="LKL" description="vbd ah">vbd ah</SCANLINE>

    <SCANLINE hits="2" mnemonic="LKL" description="vbd j">vbd j</SCANLINE>

    <SCANLINE hits="1" mnemonic="LKL" description="vbd lg">vbd lg</SCANLINE>

    <SCANLINE hits="1" mnemonic="LKL" description="vbd ru">vbd ru</SCANLINE>

    <SCANLINE hits="1" mnemonic="LKL" description="vbd2 ddr">vbd2 ddr</SCANLINE>

    <SCANLINE hits="3" mnemonic="LKL" description="vbe">vbe</SCANLINE>

    <SCANLINE hits="326" mnemonic="LKL" description="vbe 000">vbe 000</SCANLINE>

    <SCANLINE hits="7" mnemonic="LKL" description="vbf">vbf</SCANLINE>

    <SCANLINE hits="178" mnemonic="LKL" description="vbf 000">vbf 000</SCANLINE>

    <SCANLINE hits="1" mnemonic="LKL" description="vbf m">vbf m</SCANLINE>

    <SCANLINE hits="1" mnemonic="LKL" description="vbf ru">vbf ru</SCANLINE>

    <SCANLINE hits="1" mnemonic="LKL" description="vbf16 gb">vbf16 gb</SCANLINE>

    <SCANLINE hits="1" mnemonic="LKL" description="vbf76 aust">vbf76 aust</SCANLINE>

    <SCANLINE hits="66" mnemonic="LKL" description="vbg 000">vbg 000</SCANLINE>

    <SCANLINE hits="45" mnemonic="LKL" description="vbg 100">vbg 100</SCANLINE>

    <SCANLINE hits="11" mnemonic="LKL" description="vbg 200">vbg 200</SCANLINE>

    <SCANLINE hits="2" mnemonic="LKL" description="vbh">vbh</SCANLINE>

    <SCANLINE hits="211" mnemonic="LKL" description="vbh 000">vbh 000</SCANLINE>

    <SCANLINE hits="18" mnemonic="LKL" description="vbi 000">vbi 000</SCANLINE>

    <SCANLINE hits="12" mnemonic="LKL" description="vbj">vbj</SCANLINE>

    <SCANLINE hits="170" mnemonic="LKL" description="vbj 000">vbj 000</SCANLINE>

    <SCANLINE hits="4" mnemonic="LKL" description="vbj 200">vbj 200</SCANLINE>

    <SCANLINE hits="3" mnemonic="LKL" description="vbj 200 m (fh)">vbj 200 m (fh)</SCANLINE>

    <SCANLINE hits="2" mnemonic="LKL" description="vbj d (fh)">vbj d (fh)</SCANLINE>

    <SCANLINE hits="1" mnemonic="LKL" description="vbj h (fh)">vbj h (fh)</SCANLINE>

    <SCANLINE hits="1" mnemonic="LKL" description="vbj i (fh)">vbj i (fh)</SCANLINE>

    <SCANLINE hits="5" mnemonic="LKL" description="vbj k (fh)">vbj k (fh)</SCANLINE>

    <SCANLINE hits="1" mnemonic="LKL" description="vbj lg">vbj lg</SCANLINE>

    <SCANLINE hits="1" mnemonic="LKL" description="vbj16 gb">vbj16 gb</SCANLINE>

    <SCANLINE hits="1" mnemonic="LKL" description="vbj16 udssr">vbj16 udssr</SCANLINE>

    <SCANLINE hits="1" mnemonic="LKL" description="vbj66 usa">vbj66 usa</SCANLINE>

    <SCANLINE hits="6" mnemonic="LKL" description="vbk 000">vbk 000</SCANLINE>

    <SCANLINE hits="6" mnemonic="LKL" description="vbl">vbl</SCANLINE>

    <SCANLINE hits="73" mnemonic="LKL" description="vbl 000">vbl 000</SCANLINE>

    <SCANLINE hits="3" mnemonic="LKL" description="vbl 200">vbl 200</SCANLINE>

    <SCANLINE hits="110" mnemonic="LKL" description="vbl 500">vbl 500</SCANLINE>

    <SCANLINE hits="137" mnemonic="LKL" description="vbm 000">vbm 000</SCANLINE>

    <SCANLINE hits="1" mnemonic="LKL" description="vbn">vbn</SCANLINE>

    <SCANLINE hits="54" mnemonic="LKL" description="vbn 000">vbn 000</SCANLINE>

    <SCANLINE hits="18" mnemonic="LKL" description="vbn 100">vbn 100</SCANLINE>

    <SCANLINE hits="95" mnemonic="LKL" description="vbn 200">vbn 200</SCANLINE>

    <SCANLINE hits="22" mnemonic="LKL" description="vbn 300">vbn 300</SCANLINE>

    <SCANLINE hits="56" mnemonic="LKL" description="vbn 400">vbn 400</SCANLINE>

    <SCANLINE hits="319" mnemonic="LKL" description="vbn 500">vbn 500</SCANLINE>

    <SCANLINE hits="1" mnemonic="LKL" description="vbn ru">vbn ru</SCANLINE>

    <SCANLINE hits="1" mnemonic="LKL" description="vbn66 usa">vbn66 usa</SCANLINE>

    <SCANLINE hits="254" mnemonic="LKL" description="vbo 000">vbo 000</SCANLINE>

    <SCANLINE hits="50" mnemonic="LKL" description="vbp">vbp</SCANLINE>

    <SCANLINE hits="126" mnemonic="LKL" description="vbp 000">vbp 000</SCANLINE>

    <SCANLINE hits="129" mnemonic="LKL" description="vbp 100">vbp 100</SCANLINE>

    <SCANLINE hits="131" mnemonic="LKL" description="vbp 200">vbp 200</SCANLINE>

    <SCANLINE hits="7" mnemonic="LKL" description="vbp 300">vbp 300</SCANLINE>

    <SCANLINE hits="239" mnemonic="LKL" description="vbp 400">vbp 400</SCANLINE>

    <SCANLINE hits="188" mnemonic="LKL" description="vbp 500">vbp 500</SCANLINE>

    <SCANLINE hits="1" mnemonic="LKL" description="vbp 56">vbp 56</SCANLINE>

    <SCANLINE hits="17" mnemonic="LKL" description="vbp 600">vbp 600</SCANLINE>

    <SCANLINE hits="13" mnemonic="LKL" description="vbp 700">vbp 700</SCANLINE>

    <SCANLINE hits="107" mnemonic="LKL" description="vbp 800">vbp 800</SCANLINE>

    <SCANLINE hits="104" mnemonic="LKL" description="vbp 900">vbp 900</SCANLINE>

    <SCANLINE hits="1" mnemonic="LKL" description="vbp a">vbp a</SCANLINE>

    <SCANLINE hits="1" mnemonic="LKL" description="vbp j">vbp j</SCANLINE>

    <SCANLINE hits="1" mnemonic="LKL" description="vbp js">vbp js</SCANLINE>

    <SCANLINE hits="1" mnemonic="LKL" description="vbp16 gb">vbp16 gb</SCANLINE>

    <SCANLINE hits="1" mnemonic="LKL" description="vbp16 oest">vbp16 oest</SCANLINE>

    <SCANLINE hits="1" mnemonic="LKL" description="vbp46 ind">vbp46 ind</SCANLINE>

    <SCANLINE hits="1" mnemonic="LKL" description="vbp7 aust">vbp7 aust</SCANLINE>

    <SCANLINE hits="17" mnemonic="LKL" description="vbq">vbq</SCANLINE>

    <SCANLINE hits="373" mnemonic="LKL" description="vbq 000">vbq 000</SCANLINE>

    <SCANLINE hits="195" mnemonic="LKL" description="vbq 100">vbq 100</SCANLINE>

    <SCANLINE hits="102" mnemonic="LKL" description="vbq 200">vbq 200</SCANLINE>

    <SCANLINE hits="105" mnemonic="LKL" description="vbq 300">vbq 300</SCANLINE>

    <SCANLINE hits="163" mnemonic="LKL" description="vbq 400">vbq 400</SCANLINE>

    <SCANLINE hits="2" mnemonic="LKL" description="vbq 4000">vbq 4000</SCANLINE>

    <SCANLINE hits="7" mnemonic="LKL" description="vbq 500">vbq 500</SCANLINE>

    <SCANLINE hits="14" mnemonic="LKL" description="vbq 700">vbq 700</SCANLINE>

    <SCANLINE hits="72" mnemonic="LKL" description="vbq 800">vbq 800</SCANLINE>

    <SCANLINE hits="346" mnemonic="LKL" description="vbq 900">vbq 900</SCANLINE>

    <SCANLINE hits="2" mnemonic="LKL" description="vbq a">vbq a</SCANLINE>

    <SCANLINE hits="14" mnemonic="LKL" description="vbr">vbr</SCANLINE>

    <SCANLINE hits="32" mnemonic="LKL" description="vbr 000">vbr 000</SCANLINE>

    <SCANLINE hits="1" mnemonic="LKL" description="vbr ru">vbr ru</SCANLINE>

    <SCANLINE hits="1" mnemonic="LKL" description="vbr,tx">vbr,tx</SCANLINE>

    <SCANLINE hits="1" mnemonic="LKL" description="vbr66 kan">vbr66 kan</SCANLINE>

    <SCANLINE hits="4" mnemonic="LKL" description="vbs">vbs</SCANLINE>

    <SCANLINE hits="609" mnemonic="LKL" description="vbs 000">vbs 000</SCANLINE>

    <SCANLINE hits="108" mnemonic="LKL" description="vbs 100">vbs 100</SCANLINE>

    <SCANLINE hits="1" mnemonic="LKL" description="vbs 6 can">vbs 6 can</SCANLINE>

    <SCANLINE hits="31" mnemonic="LKL" description="vbs 900">vbs 900</SCANLINE>

    <SCANLINE hits="4" mnemonic="LKL" description="vbt">vbt</SCANLINE>

    <SCANLINE hits="146" mnemonic="LKL" description="vbt 000">vbt 000</SCANLINE>

    <SCANLINE hits="1" mnemonic="LKL" description="vbt e (fh)">vbt e (fh)</SCANLINE>

    <SCANLINE hits="2" mnemonic="LKL" description="vbt k (fh)">vbt k (fh)</SCANLINE>

    <SCANLINE hits="1" mnemonic="LKL" description="vbt m (fh)">vbt m (fh)</SCANLINE>

    <SCANLINE hits="1" mnemonic="LKL" description="vbu">vbu</SCANLINE>

    <SCANLINE hits="7" mnemonic="LKL" description="vbu 000">vbu 000</SCANLINE>

    <SCANLINE hits="1" mnemonic="LKL" description="vbu k (fh)">vbu k (fh)</SCANLINE>

    <SCANLINE hits="1" mnemonic="LKL" description="vbv">vbv</SCANLINE>

    <SCANLINE hits="23" mnemonic="LKL" description="vbv 000">vbv 000</SCANLINE>

    <SCANLINE hits="1" mnemonic="LKL" description="vbv m (fh)">vbv m (fh)</SCANLINE>

    <SCANLINE hits="4" mnemonic="LKL" description="vbw 000">vbw 000</SCANLINE>

    <SCANLINE hits="6" mnemonic="LKL" description="vby 000">vby 000</SCANLINE>

    <SCANLINE hits="4" mnemonic="LKL" description="vbz">vbz</SCANLINE>

    <SCANLINE hits="16" mnemonic="LKL" description="vc">vc</SCANLINE>

    <SCANLINE hits="87" mnemonic="LKL" description="vc 000">vc 000</SCANLINE>

    <SCANLINE hits="1" mnemonic="LKL" description="vc 06 udssr">vc 06 udssr</SCANLINE>

    <SCANLINE hits="3" mnemonic="LKL" description="vc a">vc a</SCANLINE>

    <SCANLINE hits="1" mnemonic="LKL" description="vc c">vc c</SCANLINE>

    <SCANLINE hits="1" mnemonic="LKL" description="vc jk">vc jk</SCANLINE>

    <SCANLINE hits="1" mnemonic="LKL" description="vc z">vc z</SCANLINE>

    <SCANLINE hits="1" mnemonic="LKL" description="vca">vca</SCANLINE>

    <SCANLINE hits="90" mnemonic="LKL" description="vca 000">vca 000</SCANLINE>

    <SCANLINE hits="20" mnemonic="LKL" description="vca 100">vca 100</SCANLINE>

    <SCANLINE hits="11" mnemonic="LKL" description="vca 110">vca 110</SCANLINE>

    <SCANLINE hits="6" mnemonic="LKL" description="vca 120">vca 120</SCANLINE>

    <SCANLINE hits="6" mnemonic="LKL" description="vca 200">vca 200</SCANLINE>

    <SCANLINE hits="5" mnemonic="LKL" description="vca 300">vca 300</SCANLINE>

    <SCANLINE hits="2" mnemonic="LKL" description="vca 320">vca 320</SCANLINE>

    <SCANLINE hits="2" mnemonic="LKL" description="vca 340">vca 340</SCANLINE>

    <SCANLINE hits="2" mnemonic="LKL" description="vca 360">vca 360</SCANLINE>

    <SCANLINE hits="2" mnemonic="LKL" description="vca 400">vca 400</SCANLINE>

    <SCANLINE hits="3" mnemonic="LKL" description="vca 410">vca 410</SCANLINE>

    <SCANLINE hits="4" mnemonic="LKL" description="vca 420">vca 420</SCANLINE>

    <SCANLINE hits="5" mnemonic="LKL" description="vca 430">vca 430</SCANLINE>

    <SCANLINE hits="8" mnemonic="LKL" description="vca 500">vca 500</SCANLINE>

    <SCANLINE hits="10" mnemonic="LKL" description="vca 510">vca 510</SCANLINE>

    <SCANLINE hits="119" mnemonic="LKL" description="vca 520">vca 520</SCANLINE>

    <SCANLINE hits="2" mnemonic="LKL" description="vcb">vcb</SCANLINE>

    <SCANLINE hits="230" mnemonic="LKL" description="vcb 000">vcb 000</SCANLINE>

    <SCANLINE hits="2" mnemonic="LKL" description="vcb js">vcb js</SCANLINE>

    <SCANLINE hits="43" mnemonic="LKL" description="vd">vd</SCANLINE>

    <SCANLINE hits="140" mnemonic="LKL" description="vd 000">vd 000</SCANLINE>

    <SCANLINE hits="1" mnemonic="LKL" description="vd 16 span">vd 16 span</SCANLINE>

    <SCANLINE hits="1" mnemonic="LKL" description="vd 46 tue">vd 46 tue</SCANLINE>

    <SCANLINE hits="1" mnemonic="LKL" description="vd 51 saf">vd 51 saf</SCANLINE>

    <SCANLINE hits="1" mnemonic="LKL" description="vd 66 usa">vd 66 usa</SCANLINE>

    <SCANLINE hits="1" mnemonic="LKL" description="vd a">vd a</SCANLINE>

    <SCANLINE hits="2" mnemonic="LKL" description="vd b">vd b</SCANLINE>

    <SCANLINE hits="2" mnemonic="LKL" description="vd c">vd c</SCANLINE>

    <SCANLINE hits="1" mnemonic="LKL" description="vd hd">vd hd</SCANLINE>

    <SCANLINE hits="1" mnemonic="LKL" description="vd jk">vd jk</SCANLINE>

    <SCANLINE hits="1" mnemonic="LKL" description="vd kq">vd kq</SCANLINE>

    <SCANLINE hits="2" mnemonic="LKL" description="vd ld">vd ld</SCANLINE>

    <SCANLINE hits="3" mnemonic="LKL" description="vd lg">vd lg</SCANLINE>

    <SCANLINE hits="1" mnemonic="LKL" description="vd ng">vd ng</SCANLINE>

    <SCANLINE hits="2" mnemonic="LKL" description="vd rr">vd rr</SCANLINE>

    <SCANLINE hits="1" mnemonic="LKL" description="vd ru">vd ru</SCANLINE>

    <SCANLINE hits="1" mnemonic="LKL" description="vd uc">vd uc</SCANLINE>

    <SCANLINE hits="2" mnemonic="LKL" description="vd vc">vd vc</SCANLINE>

    <SCANLINE hits="1" mnemonic="LKL" description="vd16pol">vd16pol</SCANLINE>

    <SCANLINE hits="3" mnemonic="LKL" description="vda">vda</SCANLINE>

    <SCANLINE hits="106" mnemonic="LKL" description="vda 000">vda 000</SCANLINE>

    <SCANLINE hits="1" mnemonic="LKL" description="vda 100">vda 100</SCANLINE>

    <SCANLINE hits="1" mnemonic="LKL" description="vda16 udssr">vda16 udssr</SCANLINE>

    <SCANLINE hits="1" mnemonic="LKL" description="vda2 brd">vda2 brd</SCANLINE>

    <SCANLINE hits="1" mnemonic="LKL" description="vdb">vdb</SCANLINE>

    <SCANLINE hits="16" mnemonic="LKL" description="vdb 000">vdb 000</SCANLINE>

    <SCANLINE hits="45" mnemonic="LKL" description="vdb 100">vdb 100</SCANLINE>

    <SCANLINE hits="2" mnemonic="LKL" description="vdb 300">vdb 300</SCANLINE>

    <SCANLINE hits="4" mnemonic="LKL" description="vdb 500">vdb 500</SCANLINE>

    <SCANLINE hits="12" mnemonic="LKL" description="vdc">vdc</SCANLINE>

    <SCANLINE hits="166" mnemonic="LKL" description="vdc 000">vdc 000</SCANLINE>

    <SCANLINE hits="1" mnemonic="LKL" description="vdc j">vdc j</SCANLINE>

    <SCANLINE hits="1" mnemonic="LKL" description="vdc lg">vdc lg</SCANLINE>

    <SCANLINE hits="1" mnemonic="LKL" description="vdc16 gb">vdc16 gb</SCANLINE>

    <SCANLINE hits="1" mnemonic="LKL" description="vdc16 ndl">vdc16 ndl</SCANLINE>

    <SCANLINE hits="43" mnemonic="LKL" description="vdd 000">vdd 000</SCANLINE>

    <SCANLINE hits="131" mnemonic="LKL" description="vde 000">vde 000</SCANLINE>

    <SCANLINE hits="40" mnemonic="LKL" description="vdf 000">vdf 000</SCANLINE>

    <SCANLINE hits="66" mnemonic="LKL" description="vdg 000">vdg 000</SCANLINE>

    <SCANLINE hits="19" mnemonic="LKL" description="vdg 100">vdg 100</SCANLINE>

    <SCANLINE hits="37" mnemonic="LKL" description="vdg 200">vdg 200</SCANLINE>

    <SCANLINE hits="8" mnemonic="LKL" description="vdg 210">vdg 210</SCANLINE>

    <SCANLINE hits="43" mnemonic="LKL" description="vdg 300">vdg 300</SCANLINE>

    <SCANLINE hits="2" mnemonic="LKL" description="vdg 310">vdg 310</SCANLINE>

    <SCANLINE hits="6" mnemonic="LKL" description="vdg 320">vdg 320</SCANLINE>

    <SCANLINE hits="32" mnemonic="LKL" description="vdg 400">vdg 400</SCANLINE>

    <SCANLINE hits="1" mnemonic="LKL" description="vdg 46 ch d">vdg 46 ch d</SCANLINE>

    <SCANLINE hits="31" mnemonic="LKL" description="vdg 500">vdg 500</SCANLINE>

    <SCANLINE hits="60" mnemonic="LKL" description="vdg 600">vdg 600</SCANLINE>

    <SCANLINE hits="16" mnemonic="LKL" description="vdg 610">vdg 610</SCANLINE>

    <SCANLINE hits="9" mnemonic="LKL" description="vdg 620">vdg 620</SCANLINE>

    <SCANLINE hits="14" mnemonic="LKL" description="vdg 630">vdg 630</SCANLINE>

    <SCANLINE hits="57" mnemonic="LKL" description="vdg 700">vdg 700</SCANLINE>

    <SCANLINE hits="27" mnemonic="LKL" description="vdg 710">vdg 710</SCANLINE>

    <SCANLINE hits="24" mnemonic="LKL" description="vdg 720">vdg 720</SCANLINE>

    <SCANLINE hits="27" mnemonic="LKL" description="vdg 730">vdg 730</SCANLINE>

    <SCANLINE hits="88" mnemonic="LKL" description="vdg 800">vdg 800</SCANLINE>

    <SCANLINE hits="29" mnemonic="LKL" description="vdg 810">vdg 810</SCANLINE>

    <SCANLINE hits="37" mnemonic="LKL" description="vdg 820">vdg 820</SCANLINE>

    <SCANLINE hits="18" mnemonic="LKL" description="vdg 830">vdg 830</SCANLINE>

    <SCANLINE hits="1" mnemonic="LKL" description="vdg 900">vdg 900</SCANLINE>

    <SCANLINE hits="1" mnemonic="LKL" description="vdh">vdh</SCANLINE>

    <SCANLINE hits="84" mnemonic="LKL" description="vdh 000">vdh 000</SCANLINE>

    <SCANLINE hits="53" mnemonic="LKL" description="vdh 100">vdh 100</SCANLINE>

    <SCANLINE hits="20" mnemonic="LKL" description="vdh 110">vdh 110</SCANLINE>

    <SCANLINE hits="24" mnemonic="LKL" description="vdh 120">vdh 120</SCANLINE>

    <SCANLINE hits="14" mnemonic="LKL" description="vdh 130">vdh 130</SCANLINE>

    <SCANLINE hits="80" mnemonic="LKL" description="vdh 200">vdh 200</SCANLINE>

    <SCANLINE hits="20" mnemonic="LKL" description="vdh 210">vdh 210</SCANLINE>

    <SCANLINE hits="31" mnemonic="LKL" description="vdh 220">vdh 220</SCANLINE>

    <SCANLINE hits="32" mnemonic="LKL" description="vdh 230">vdh 230</SCANLINE>

    <SCANLINE hits="127" mnemonic="LKL" description="vdh 300">vdh 300</SCANLINE>

    <SCANLINE hits="52" mnemonic="LKL" description="vdh 310">vdh 310</SCANLINE>

    <SCANLINE hits="66" mnemonic="LKL" description="vdh 320">vdh 320</SCANLINE>

    <SCANLINE hits="1" mnemonic="LKL" description="vdh 330">vdh 330</SCANLINE>

    <SCANLINE hits="25" mnemonic="LKL" description="vdh 400">vdh 400</SCANLINE>

    <SCANLINE hits="1" mnemonic="LKL" description="vdh 410">vdh 410</SCANLINE>

    <SCANLINE hits="1" mnemonic="LKL" description="vdh 700">vdh 700</SCANLINE>

    <SCANLINE hits="103" mnemonic="LKL" description="vdi 000">vdi 000</SCANLINE>

    <SCANLINE hits="57" mnemonic="LKL" description="vdi 100">vdi 100</SCANLINE>

    <SCANLINE hits="41" mnemonic="LKL" description="vdi 110">vdi 110</SCANLINE>

    <SCANLINE hits="9" mnemonic="LKL" description="vdi 111">vdi 111</SCANLINE>

    <SCANLINE hits="26" mnemonic="LKL" description="vdi 112">vdi 112</SCANLINE>

    <SCANLINE hits="28" mnemonic="LKL" description="vdi 113">vdi 113</SCANLINE>

    <SCANLINE hits="48" mnemonic="LKL" description="vdi 120">vdi 120</SCANLINE>

    <SCANLINE hits="56" mnemonic="LKL" description="vdi 121">vdi 121</SCANLINE>

    <SCANLINE hits="16" mnemonic="LKL" description="vdi 122">vdi 122</SCANLINE>

    <SCANLINE hits="314" mnemonic="LKL" description="vdi 200">vdi 200</SCANLINE>

    <SCANLINE hits="88" mnemonic="LKL" description="vdi 210">vdi 210</SCANLINE>

    <SCANLINE hits="120" mnemonic="LKL" description="vdi 220">vdi 220</SCANLINE>

    <SCANLINE hits="5" mnemonic="LKL" description="vdl">vdl</SCANLINE>

    <SCANLINE hits="1" mnemonic="LKL" description="vdm 300">vdm 300</SCANLINE>

    <SCANLINE hits="2" mnemonic="LKL" description="vdn">vdn</SCANLINE>

    <SCANLINE hits="2" mnemonic="LKL" description="vdo">vdo</SCANLINE>

    <SCANLINE hits="1" mnemonic="LKL" description="vdo a">vdo a</SCANLINE>

    <SCANLINE hits="1" mnemonic="LKL" description="vdp">vdp</SCANLINE>

    <SCANLINE hits="1" mnemonic="LKL" description="vdp16 span vds16 span ve 16 span">vdp16 span vds16 span ve 16 span</SCANLINE>

    <SCANLINE hits="3" mnemonic="LKL" description="vdr">vdr</SCANLINE>

    <SCANLINE hits="1" mnemonic="LKL" description="vds">vds</SCANLINE>

    <SCANLINE hits="2" mnemonic="LKL" description="vdt">vdt</SCANLINE>

    <SCANLINE hits="2" mnemonic="LKL" description="vdu">vdu</SCANLINE>

    <SCANLINE hits="6" mnemonic="LKL" description="vdx">vdx</SCANLINE>

    <SCANLINE hits="1" mnemonic="LKL" description="vdx 41">vdx 41</SCANLINE>

    <SCANLINE hits="4" mnemonic="LKL" description="vdx mb">vdx mb</SCANLINE>

    <SCANLINE hits="1" mnemonic="LKL" description="vdx16 gb">vdx16 gb</SCANLINE>

    <SCANLINE hits="37" mnemonic="LKL" description="vdz">vdz</SCANLINE>

    <SCANLINE hits="1" mnemonic="LKL" description="vdz 11 d">vdz 11 d</SCANLINE>

    <SCANLINE hits="1" mnemonic="LKL" description="vdz 16 nd">vdz 16 nd</SCANLINE>

    <SCANLINE hits="1" mnemonic="LKL" description="vdz 16 pol">vdz 16 pol</SCANLINE>

    <SCANLINE hits="1" mnemonic="LKL" description="vdz 16 sp">vdz 16 sp</SCANLINE>

    <SCANLINE hits="1" mnemonic="LKL" description="vdz 61">vdz 61</SCANLINE>

    <SCANLINE hits="1" mnemonic="LKL" description="vdz a">vdz a</SCANLINE>

    <SCANLINE hits="4" mnemonic="LKL" description="vdz ab">vdz ab</SCANLINE>

    <SCANLINE hits="2" mnemonic="LKL" description="vdz c">vdz c</SCANLINE>

    <SCANLINE hits="1" mnemonic="LKL" description="vdz cc">vdz cc</SCANLINE>

    <SCANLINE hits="1" mnemonic="LKL" description="vdz d">vdz d</SCANLINE>

    <SCANLINE hits="2" mnemonic="LKL" description="vdz gx">vdz gx</SCANLINE>

    <SCANLINE hits="1" mnemonic="LKL" description="vdz hs">vdz hs</SCANLINE>

    <SCANLINE hits="1" mnemonic="LKL" description="vdz kk">vdz kk</SCANLINE>

    <SCANLINE hits="2" mnemonic="LKL" description="vdz ld">vdz ld</SCANLINE>

    <SCANLINE hits="2" mnemonic="LKL" description="vdz lg">vdz lg</SCANLINE>

    <SCANLINE hits="1" mnemonic="LKL" description="vdz ou">vdz ou</SCANLINE>

    <SCANLINE hits="1" mnemonic="LKL" description="vdz ru">vdz ru</SCANLINE>

    <SCANLINE hits="1" mnemonic="LKL" description="vdz16 frank ty 16 frank">vdz16 frank ty 16 frank</SCANLINE>

    <SCANLINE hits="1" mnemonic="LKL" description="vdz16 schwd">vdz16 schwd</SCANLINE>

    <SCANLINE hits="2" mnemonic="LKL" description="vdz2 d var2 d">vdz2 d var2 d</SCANLINE>

    <SCANLINE hits="1" mnemonic="LKL" description="vdz66 kan">vdz66 kan</SCANLINE>

    <SCANLINE hits="1064" mnemonic="LKL" description="ve">ve</SCANLINE>

    <SCANLINE hits="25" mnemonic="LKL" description="ve 000">ve 000</SCANLINE>

    <SCANLINE hits="1" mnemonic="LKL" description="ve 01">ve 01</SCANLINE>

    <SCANLINE hits="1" mnemonic="LKL" description="ve 01 mittelmeergebiet">ve 01 mittelmeergebiet</SCANLINE>

    <SCANLINE hits="4" mnemonic="LKL" description="ve 06 udssr">ve 06 udssr</SCANLINE>

    <SCANLINE hits="2" mnemonic="LKL" description="ve 06 ussr">ve 06 ussr</SCANLINE>

    <SCANLINE hits="1" mnemonic="LKL" description="ve 1 daen">ve 1 daen</SCANLINE>

    <SCANLINE hits="1" mnemonic="LKL" description="ve 11">ve 11</SCANLINE>

    <SCANLINE hits="1" mnemonic="LKL" description="ve 11 97">ve 11 97</SCANLINE>

    <SCANLINE hits="1" mnemonic="LKL" description="ve 11 we vz 11 we">ve 11 we vz 11 we</SCANLINE>

    <SCANLINE hits="1" mnemonic="LKL" description="ve 113b">ve 113b</SCANLINE>

    <SCANLINE hits="2" mnemonic="LKL" description="ve 16">ve 16</SCANLINE>

    <SCANLINE hits="1" mnemonic="LKL" description="ve 16 aest">ve 16 aest</SCANLINE>

    <SCANLINE hits="1" mnemonic="LKL" description="ve 16 alb">ve 16 alb</SCANLINE>

    <SCANLINE hits="3" mnemonic="LKL" description="ve 16 belg">ve 16 belg</SCANLINE>

    <SCANLINE hits="1" mnemonic="LKL" description="ve 16 belg ve 46 malay">ve 16 belg ve 46 malay</SCANLINE>

    <SCANLINE hits="3" mnemonic="LKL" description="ve 16 belg vz 16 belg ud 16 belg">ve 16 belg vz 16 belg ud 16 belg</SCANLINE>

    <SCANLINE hits="2" mnemonic="LKL" description="ve 16 bulg">ve 16 bulg</SCANLINE>

    <SCANLINE hits="1" mnemonic="LKL" description="ve 16 dae">ve 16 dae</SCANLINE>

    <SCANLINE hits="4" mnemonic="LKL" description="ve 16 daen">ve 16 daen</SCANLINE>

    <SCANLINE hits="1" mnemonic="LKL" description="ve 16 dan">ve 16 dan</SCANLINE>

    <SCANLINE hits="3" mnemonic="LKL" description="ve 16 deutsches reich">ve 16 deutsches reich</SCANLINE>

    <SCANLINE hits="1" mnemonic="LKL" description="ve 16 fin">ve 16 fin</SCANLINE>

    <SCANLINE hits="5" mnemonic="LKL" description="ve 16 finn">ve 16 finn</SCANLINE>

    <SCANLINE hits="1" mnemonic="LKL" description="ve 16 fra">ve 16 fra</SCANLINE>

    <SCANLINE hits="20" mnemonic="LKL" description="ve 16 frank">ve 16 frank</SCANLINE>

    <SCANLINE hits="1" mnemonic="LKL" description="ve 16 frank vad16 frank">ve 16 frank vad16 frank</SCANLINE>

    <SCANLINE hits="1" mnemonic="LKL" description="ve 16 frank vd 16 frank">ve 16 frank vd 16 frank</SCANLINE>

    <SCANLINE hits="1" mnemonic="LKL" description="ve 16 frank vz 16 frank vdt16 frank">ve 16 frank vz 16 frank vdt16 frank</SCANLINE>

    <SCANLINE hits="7" mnemonic="LKL" description="ve 16 gb">ve 16 gb</SCANLINE>

</SCANLIST>

<SCANPREV term="vao+ly" />


<SCANNEXT term="ve+16+gb" />

</RESULT>
