<?xml version="1.0" encoding="UTF-8" ?>
<RESULT>
<SESSION><SESSIONVAR name="LNG">DU</SESSIONVAR>
<SESSIONVAR name="DB">1</SESSIONVAR>
<SESSIONVAR name="SID">d7eaccbe-2</SESSIONVAR>


<SESSIONVAR name="TITLE">G%26ouml%3Bttinger+Universit%26auml%3Btskatalog+(GUK)</SESSIONVAR>
</SESSION>
<SCANLIST>

    <SCANLINE hits="66" mnemonic="LKL" description="uri 800">uri 800</SCANLINE>

    <SCANLINE hits="21" mnemonic="LKL" description="uri 900">uri 900</SCANLINE>

    <SCANLINE hits="21" mnemonic="LKL" description="urj 000">urj 000</SCANLINE>

    <SCANLINE hits="4" mnemonic="LKL" description="urj 050">urj 050</SCANLINE>

    <SCANLINE hits="87" mnemonic="LKL" description="urj 100">urj 100</SCANLINE>

    <SCANLINE hits="65" mnemonic="LKL" description="urj 150">urj 150</SCANLINE>

    <SCANLINE hits="45" mnemonic="LKL" description="urj 170">urj 170</SCANLINE>

    <SCANLINE hits="129" mnemonic="LKL" description="urj 200">urj 200</SCANLINE>

    <SCANLINE hits="4" mnemonic="LKL" description="urj 300">urj 300</SCANLINE>

    <SCANLINE hits="16" mnemonic="LKL" description="urj 400">urj 400</SCANLINE>

    <SCANLINE hits="37" mnemonic="LKL" description="urj 500">urj 500</SCANLINE>

    <SCANLINE hits="34" mnemonic="LKL" description="urk 000">urk 000</SCANLINE>

    <SCANLINE hits="11" mnemonic="LKL" description="urk 050">urk 050</SCANLINE>

    <SCANLINE hits="11" mnemonic="LKL" description="urk 100">urk 100</SCANLINE>

    <SCANLINE hits="33" mnemonic="LKL" description="urk 200">urk 200</SCANLINE>

    <SCANLINE hits="21" mnemonic="LKL" description="urk 300">urk 300</SCANLINE>

    <SCANLINE hits="13" mnemonic="LKL" description="urk 400">urk 400</SCANLINE>

    <SCANLINE hits="28" mnemonic="LKL" description="urk 500">urk 500</SCANLINE>

    <SCANLINE hits="46" mnemonic="LKL" description="urk 600">urk 600</SCANLINE>

    <SCANLINE hits="52" mnemonic="LKL" description="urk 700">urk 700</SCANLINE>

    <SCANLINE hits="4" mnemonic="LKL" description="urk 730">urk 730</SCANLINE>

    <SCANLINE hits="2" mnemonic="LKL" description="urk 800">urk 800</SCANLINE>

    <SCANLINE hits="13" mnemonic="LKL" description="urk 900">urk 900</SCANLINE>

    <SCANLINE hits="18" mnemonic="LKL" description="url 000">url 000</SCANLINE>

    <SCANLINE hits="3" mnemonic="LKL" description="url 050">url 050</SCANLINE>

    <SCANLINE hits="154" mnemonic="LKL" description="url 100">url 100</SCANLINE>

    <SCANLINE hits="66" mnemonic="LKL" description="url 150">url 150</SCANLINE>

    <SCANLINE hits="5" mnemonic="LKL" description="url 200">url 200</SCANLINE>

    <SCANLINE hits="13" mnemonic="LKL" description="url 300">url 300</SCANLINE>

    <SCANLINE hits="5" mnemonic="LKL" description="url 330">url 330</SCANLINE>

    <SCANLINE hits="25" mnemonic="LKL" description="url 350">url 350</SCANLINE>

    <SCANLINE hits="52" mnemonic="LKL" description="url 400">url 400</SCANLINE>

    <SCANLINE hits="176" mnemonic="LKL" description="url 410">url 410</SCANLINE>

    <SCANLINE hits="18" mnemonic="LKL" description="url 500">url 500</SCANLINE>

    <SCANLINE hits="24" mnemonic="LKL" description="url 600">url 600</SCANLINE>

    <SCANLINE hits="9" mnemonic="LKL" description="urm 000">urm 000</SCANLINE>

    <SCANLINE hits="2" mnemonic="LKL" description="urm 100">urm 100</SCANLINE>

    <SCANLINE hits="4" mnemonic="LKL" description="urm 108">urm 108</SCANLINE>

    <SCANLINE hits="8" mnemonic="LKL" description="urm 110">urm 110</SCANLINE>

    <SCANLINE hits="37" mnemonic="LKL" description="urm 113">urm 113</SCANLINE>

    <SCANLINE hits="4" mnemonic="LKL" description="urm 115">urm 115</SCANLINE>

    <SCANLINE hits="9" mnemonic="LKL" description="urm 120">urm 120</SCANLINE>

    <SCANLINE hits="14" mnemonic="LKL" description="urm 200">urm 200</SCANLINE>

    <SCANLINE hits="6" mnemonic="LKL" description="urm 300">urm 300</SCANLINE>

    <SCANLINE hits="2" mnemonic="LKL" description="urm 400">urm 400</SCANLINE>

    <SCANLINE hits="47" mnemonic="LKL" description="urm 500">urm 500</SCANLINE>

    <SCANLINE hits="87" mnemonic="LKL" description="urn 000">urn 000</SCANLINE>

    <SCANLINE hits="41" mnemonic="LKL" description="uro 000">uro 000</SCANLINE>

    <SCANLINE hits="3" mnemonic="LKL" description="uro 100">uro 100</SCANLINE>

    <SCANLINE hits="91" mnemonic="LKL" description="uro 120">uro 120</SCANLINE>

    <SCANLINE hits="87" mnemonic="LKL" description="uro 130">uro 130</SCANLINE>

    <SCANLINE hits="36" mnemonic="LKL" description="uro 140">uro 140</SCANLINE>

    <SCANLINE hits="3" mnemonic="LKL" description="uro 300">uro 300</SCANLINE>

    <SCANLINE hits="5" mnemonic="LKL" description="uro 330">uro 330</SCANLINE>

    <SCANLINE hits="58" mnemonic="LKL" description="uro 354">uro 354</SCANLINE>

    <SCANLINE hits="111" mnemonic="LKL" description="uro 356">uro 356</SCANLINE>

    <SCANLINE hits="3" mnemonic="LKL" description="uro 370">uro 370</SCANLINE>

    <SCANLINE hits="9" mnemonic="LKL" description="urp 000">urp 000</SCANLINE>

    <SCANLINE hits="25" mnemonic="LKL" description="urq 000">urq 000</SCANLINE>

    <SCANLINE hits="15" mnemonic="LKL" description="urq 100">urq 100</SCANLINE>

    <SCANLINE hits="6" mnemonic="LKL" description="urq 310">urq 310</SCANLINE>

    <SCANLINE hits="18" mnemonic="LKL" description="urq 320">urq 320</SCANLINE>

    <SCANLINE hits="5" mnemonic="LKL" description="urq 330">urq 330</SCANLINE>

    <SCANLINE hits="8" mnemonic="LKL" description="urq 340">urq 340</SCANLINE>

    <SCANLINE hits="7" mnemonic="LKL" description="urq 350">urq 350</SCANLINE>

    <SCANLINE hits="5" mnemonic="LKL" description="urq 360">urq 360</SCANLINE>

    <SCANLINE hits="38" mnemonic="LKL" description="urq 370">urq 370</SCANLINE>

    <SCANLINE hits="11" mnemonic="LKL" description="urq 380">urq 380</SCANLINE>

    <SCANLINE hits="10" mnemonic="LKL" description="urq 390">urq 390</SCANLINE>

    <SCANLINE hits="18" mnemonic="LKL" description="urq 400">urq 400</SCANLINE>

    <SCANLINE hits="28" mnemonic="LKL" description="urq 410">urq 410</SCANLINE>

    <SCANLINE hits="18" mnemonic="LKL" description="urq 420">urq 420</SCANLINE>

    <SCANLINE hits="18" mnemonic="LKL" description="urq 430">urq 430</SCANLINE>

    <SCANLINE hits="5" mnemonic="LKL" description="urq 440">urq 440</SCANLINE>

    <SCANLINE hits="11" mnemonic="LKL" description="urq 450">urq 450</SCANLINE>

    <SCANLINE hits="10" mnemonic="LKL" description="urr 000">urr 000</SCANLINE>

    <SCANLINE hits="10" mnemonic="LKL" description="urr 100">urr 100</SCANLINE>

    <SCANLINE hits="22" mnemonic="LKL" description="urr 210">urr 210</SCANLINE>

    <SCANLINE hits="45" mnemonic="LKL" description="urr 220">urr 220</SCANLINE>

    <SCANLINE hits="22" mnemonic="LKL" description="urr 230">urr 230</SCANLINE>

    <SCANLINE hits="2" mnemonic="LKL" description="urr 240">urr 240</SCANLINE>

    <SCANLINE hits="5" mnemonic="LKL" description="urr 245">urr 245</SCANLINE>

    <SCANLINE hits="30" mnemonic="LKL" description="urr 250">urr 250</SCANLINE>

    <SCANLINE hits="37" mnemonic="LKL" description="urr 260">urr 260</SCANLINE>

    <SCANLINE hits="25" mnemonic="LKL" description="urr 270">urr 270</SCANLINE>

    <SCANLINE hits="24" mnemonic="LKL" description="urs 000">urs 000</SCANLINE>

    <SCANLINE hits="40" mnemonic="LKL" description="urs 100">urs 100</SCANLINE>

    <SCANLINE hits="18" mnemonic="LKL" description="urs 200">urs 200</SCANLINE>

    <SCANLINE hits="2" mnemonic="LKL" description="urs 220">urs 220</SCANLINE>

    <SCANLINE hits="8" mnemonic="LKL" description="urs 300">urs 300</SCANLINE>

    <SCANLINE hits="9" mnemonic="LKL" description="urs 400">urs 400</SCANLINE>

    <SCANLINE hits="31" mnemonic="LKL" description="urs 500">urs 500</SCANLINE>

    <SCANLINE hits="20" mnemonic="LKL" description="urs 600">urs 600</SCANLINE>

    <SCANLINE hits="117" mnemonic="LKL" description="urs 700">urs 700</SCANLINE>

    <SCANLINE hits="19" mnemonic="LKL" description="urs 800">urs 800</SCANLINE>

    <SCANLINE hits="20" mnemonic="LKL" description="urs 900">urs 900</SCANLINE>

    <SCANLINE hits="21" mnemonic="LKL" description="urt 000">urt 000</SCANLINE>

    <SCANLINE hits="8" mnemonic="LKL" description="urt 100">urt 100</SCANLINE>

    <SCANLINE hits="46" mnemonic="LKL" description="urt 200">urt 200</SCANLINE>

    <SCANLINE hits="9" mnemonic="LKL" description="urt 300">urt 300</SCANLINE>

    <SCANLINE hits="24" mnemonic="LKL" description="urt 400">urt 400</SCANLINE>

    <SCANLINE hits="34" mnemonic="LKL" description="urt 500">urt 500</SCANLINE>

    <SCANLINE hits="44" mnemonic="LKL" description="urt 600">urt 600</SCANLINE>

    <SCANLINE hits="33" mnemonic="LKL" description="urt 700">urt 700</SCANLINE>

    <SCANLINE hits="76" mnemonic="LKL" description="urt 800">urt 800</SCANLINE>

    <SCANLINE hits="4" mnemonic="LKL" description="uru 000">uru 000</SCANLINE>

    <SCANLINE hits="19" mnemonic="LKL" description="uru 100">uru 100</SCANLINE>

    <SCANLINE hits="52" mnemonic="LKL" description="uru 200">uru 200</SCANLINE>

    <SCANLINE hits="12" mnemonic="LKL" description="urv 000">urv 000</SCANLINE>

    <SCANLINE hits="1" mnemonic="LKL" description="urw">urw</SCANLINE>

    <SCANLINE hits="92" mnemonic="LKL" description="urw 000">urw 000</SCANLINE>

    <SCANLINE hits="159" mnemonic="LKL" description="urw 200">urw 200</SCANLINE>

    <SCANLINE hits="33" mnemonic="LKL" description="urw 210">urw 210</SCANLINE>

    <SCANLINE hits="38" mnemonic="LKL" description="urw 240">urw 240</SCANLINE>

    <SCANLINE hits="52" mnemonic="LKL" description="urw 245">urw 245</SCANLINE>

    <SCANLINE hits="7" mnemonic="LKL" description="urw 250">urw 250</SCANLINE>

    <SCANLINE hits="97" mnemonic="LKL" description="urw 260">urw 260</SCANLINE>

    <SCANLINE hits="115" mnemonic="LKL" description="urw 280">urw 280</SCANLINE>

    <SCANLINE hits="13" mnemonic="LKL" description="urw 300">urw 300</SCANLINE>

    <SCANLINE hits="66" mnemonic="LKL" description="urw 320">urw 320</SCANLINE>

    <SCANLINE hits="51" mnemonic="LKL" description="urw 325">urw 325</SCANLINE>

    <SCANLINE hits="89" mnemonic="LKL" description="urw 330">urw 330</SCANLINE>

    <SCANLINE hits="178" mnemonic="LKL" description="urw 340">urw 340</SCANLINE>

    <SCANLINE hits="96" mnemonic="LKL" description="urw 350">urw 350</SCANLINE>

    <SCANLINE hits="191" mnemonic="LKL" description="urw 360">urw 360</SCANLINE>

    <SCANLINE hits="54" mnemonic="LKL" description="urw 370">urw 370</SCANLINE>

    <SCANLINE hits="2" mnemonic="LKL" description="urw 380">urw 380</SCANLINE>

    <SCANLINE hits="272" mnemonic="LKL" description="urw 400">urw 400</SCANLINE>

    <SCANLINE hits="43" mnemonic="LKL" description="urw 402">urw 402</SCANLINE>

    <SCANLINE hits="9" mnemonic="LKL" description="urw 404">urw 404</SCANLINE>

    <SCANLINE hits="10" mnemonic="LKL" description="urw 405">urw 405</SCANLINE>

    <SCANLINE hits="7" mnemonic="LKL" description="urw 406">urw 406</SCANLINE>

    <SCANLINE hits="4" mnemonic="LKL" description="urw 407">urw 407</SCANLINE>

    <SCANLINE hits="8" mnemonic="LKL" description="urw 408">urw 408</SCANLINE>

    <SCANLINE hits="8" mnemonic="LKL" description="urw 409">urw 409</SCANLINE>

    <SCANLINE hits="23" mnemonic="LKL" description="urw 410">urw 410</SCANLINE>

    <SCANLINE hits="7" mnemonic="LKL" description="urw 411">urw 411</SCANLINE>

    <SCANLINE hits="7" mnemonic="LKL" description="urw 412">urw 412</SCANLINE>

    <SCANLINE hits="3" mnemonic="LKL" description="urw 413">urw 413</SCANLINE>

    <SCANLINE hits="12" mnemonic="LKL" description="urw 414">urw 414</SCANLINE>

    <SCANLINE hits="9" mnemonic="LKL" description="urw 415">urw 415</SCANLINE>

    <SCANLINE hits="14" mnemonic="LKL" description="urw 416">urw 416</SCANLINE>

    <SCANLINE hits="14" mnemonic="LKL" description="urw 417">urw 417</SCANLINE>

    <SCANLINE hits="8" mnemonic="LKL" description="urw 418">urw 418</SCANLINE>

    <SCANLINE hits="65" mnemonic="LKL" description="urw 420">urw 420</SCANLINE>

    <SCANLINE hits="223" mnemonic="LKL" description="urw 425">urw 425</SCANLINE>

    <SCANLINE hits="217" mnemonic="LKL" description="urw 430">urw 430</SCANLINE>

    <SCANLINE hits="22" mnemonic="LKL" description="urw 440">urw 440</SCANLINE>

    <SCANLINE hits="258" mnemonic="LKL" description="urw 450">urw 450</SCANLINE>

    <SCANLINE hits="386" mnemonic="LKL" description="urw 460">urw 460</SCANLINE>

    <SCANLINE hits="139" mnemonic="LKL" description="urw 470">urw 470</SCANLINE>

    <SCANLINE hits="16" mnemonic="LKL" description="urw 475">urw 475</SCANLINE>

    <SCANLINE hits="11" mnemonic="LKL" description="urw 480">urw 480</SCANLINE>

    <SCANLINE hits="111" mnemonic="LKL" description="urw 490">urw 490</SCANLINE>

    <SCANLINE hits="21" mnemonic="LKL" description="urw 500">urw 500</SCANLINE>

    <SCANLINE hits="117" mnemonic="LKL" description="urw 510">urw 510</SCANLINE>

    <SCANLINE hits="50" mnemonic="LKL" description="urw 520">urw 520</SCANLINE>

    <SCANLINE hits="38" mnemonic="LKL" description="urw 530">urw 530</SCANLINE>

    <SCANLINE hits="24" mnemonic="LKL" description="urw 540">urw 540</SCANLINE>

    <SCANLINE hits="50" mnemonic="LKL" description="urw 550">urw 550</SCANLINE>

    <SCANLINE hits="769" mnemonic="LKL" description="urw 560">urw 560</SCANLINE>

    <SCANLINE hits="17" mnemonic="LKL" description="urw 570">urw 570</SCANLINE>

    <SCANLINE hits="31" mnemonic="LKL" description="urw 580">urw 580</SCANLINE>

    <SCANLINE hits="55" mnemonic="LKL" description="urw 590">urw 590</SCANLINE>

    <SCANLINE hits="142" mnemonic="LKL" description="urw 600">urw 600</SCANLINE>

    <SCANLINE hits="53" mnemonic="LKL" description="urw 610">urw 610</SCANLINE>

    <SCANLINE hits="192" mnemonic="LKL" description="urw 620">urw 620</SCANLINE>

    <SCANLINE hits="9" mnemonic="LKL" description="urw 630">urw 630</SCANLINE>

    <SCANLINE hits="39" mnemonic="LKL" description="urw 640">urw 640</SCANLINE>

    <SCANLINE hits="202" mnemonic="LKL" description="urw 650">urw 650</SCANLINE>

    <SCANLINE hits="48" mnemonic="LKL" description="urw 660">urw 660</SCANLINE>

    <SCANLINE hits="198" mnemonic="LKL" description="urw 670">urw 670</SCANLINE>

    <SCANLINE hits="27" mnemonic="LKL" description="urw 680">urw 680</SCANLINE>

    <SCANLINE hits="49" mnemonic="LKL" description="urw 690">urw 690</SCANLINE>

    <SCANLINE hits="164" mnemonic="LKL" description="urw 695">urw 695</SCANLINE>

    <SCANLINE hits="98" mnemonic="LKL" description="urw 700">urw 700</SCANLINE>

    <SCANLINE hits="55" mnemonic="LKL" description="urw 710">urw 710</SCANLINE>

    <SCANLINE hits="19" mnemonic="LKL" description="urw 720">urw 720</SCANLINE>

    <SCANLINE hits="73" mnemonic="LKL" description="urw 730">urw 730</SCANLINE>

    <SCANLINE hits="30" mnemonic="LKL" description="urw 740">urw 740</SCANLINE>

    <SCANLINE hits="77" mnemonic="LKL" description="urw 750">urw 750</SCANLINE>

    <SCANLINE hits="132" mnemonic="LKL" description="urw 760">urw 760</SCANLINE>

    <SCANLINE hits="38" mnemonic="LKL" description="urw 770">urw 770</SCANLINE>

    <SCANLINE hits="37" mnemonic="LKL" description="urw 780">urw 780</SCANLINE>

    <SCANLINE hits="38" mnemonic="LKL" description="urw 790">urw 790</SCANLINE>

    <SCANLINE hits="98" mnemonic="LKL" description="urw 800">urw 800</SCANLINE>

    <SCANLINE hits="61" mnemonic="LKL" description="urw 810">urw 810</SCANLINE>

    <SCANLINE hits="428" mnemonic="LKL" description="urw 820">urw 820</SCANLINE>

    <SCANLINE hits="35" mnemonic="LKL" description="urw 830">urw 830</SCANLINE>

    <SCANLINE hits="87" mnemonic="LKL" description="urw 840">urw 840</SCANLINE>

    <SCANLINE hits="101" mnemonic="LKL" description="urw 850">urw 850</SCANLINE>

    <SCANLINE hits="56" mnemonic="LKL" description="urw 860">urw 860</SCANLINE>

    <SCANLINE hits="50" mnemonic="LKL" description="urw 870">urw 870</SCANLINE>

    <SCANLINE hits="285" mnemonic="LKL" description="urw 880">urw 880</SCANLINE>

    <SCANLINE hits="4" mnemonic="LKL" description="urx 100">urx 100</SCANLINE>

    <SCANLINE hits="11" mnemonic="LKL" description="urx 130">urx 130</SCANLINE>

    <SCANLINE hits="17" mnemonic="LKL" description="urx 200">urx 200</SCANLINE>

    <SCANLINE hits="2" mnemonic="LKL" description="urx 220">urx 220</SCANLINE>

    <SCANLINE hits="134" mnemonic="LKL" description="urx 225">urx 225</SCANLINE>

    <SCANLINE hits="2" mnemonic="LKL" description="urx 230">urx 230</SCANLINE>

    <SCANLINE hits="17" mnemonic="LKL" description="urx 231">urx 231</SCANLINE>

    <SCANLINE hits="8" mnemonic="LKL" description="urx 232">urx 232</SCANLINE>

    <SCANLINE hits="16" mnemonic="LKL" description="urx 233">urx 233</SCANLINE>

    <SCANLINE hits="9" mnemonic="LKL" description="urx 234">urx 234</SCANLINE>

    <SCANLINE hits="14" mnemonic="LKL" description="urx 235">urx 235</SCANLINE>

    <SCANLINE hits="23" mnemonic="LKL" description="urx 236">urx 236</SCANLINE>

    <SCANLINE hits="13" mnemonic="LKL" description="urx 237">urx 237</SCANLINE>

    <SCANLINE hits="12" mnemonic="LKL" description="urx 240">urx 240</SCANLINE>

    <SCANLINE hits="1" mnemonic="LKL" description="urx 250">urx 250</SCANLINE>

    <SCANLINE hits="15" mnemonic="LKL" description="urx 251">urx 251</SCANLINE>

    <SCANLINE hits="6" mnemonic="LKL" description="urx 252">urx 252</SCANLINE>

    <SCANLINE hits="12" mnemonic="LKL" description="urx 253">urx 253</SCANLINE>

    <SCANLINE hits="8" mnemonic="LKL" description="urx 254">urx 254</SCANLINE>

    <SCANLINE hits="73" mnemonic="LKL" description="urx 256">urx 256</SCANLINE>

    <SCANLINE hits="52" mnemonic="LKL" description="urx 300">urx 300</SCANLINE>

    <SCANLINE hits="4" mnemonic="LKL" description="urx 350">urx 350</SCANLINE>

    <SCANLINE hits="2" mnemonic="LKL" description="urx 355">urx 355</SCANLINE>

    <SCANLINE hits="26" mnemonic="LKL" description="urx 500">urx 500</SCANLINE>

    <SCANLINE hits="91" mnemonic="LKL" description="urx 510">urx 510</SCANLINE>

    <SCANLINE hits="25" mnemonic="LKL" description="urx 520">urx 520</SCANLINE>

    <SCANLINE hits="1" mnemonic="LKL" description="urx 530">urx 530</SCANLINE>

    <SCANLINE hits="67" mnemonic="LKL" description="urx 540">urx 540</SCANLINE>

    <SCANLINE hits="37" mnemonic="LKL" description="urx 542">urx 542</SCANLINE>

    <SCANLINE hits="152" mnemonic="LKL" description="urx 543">urx 543</SCANLINE>

    <SCANLINE hits="23" mnemonic="LKL" description="urx 544">urx 544</SCANLINE>

    <SCANLINE hits="100" mnemonic="LKL" description="urx 550">urx 550</SCANLINE>

    <SCANLINE hits="178" mnemonic="LKL" description="urx 560">urx 560</SCANLINE>

    <SCANLINE hits="3" mnemonic="LKL" description="urx 570">urx 570</SCANLINE>

    <SCANLINE hits="70" mnemonic="LKL" description="urx 580">urx 580</SCANLINE>

    <SCANLINE hits="10" mnemonic="LKL" description="urx 582">urx 582</SCANLINE>

    <SCANLINE hits="11" mnemonic="LKL" description="urx 584">urx 584</SCANLINE>

    <SCANLINE hits="15" mnemonic="LKL" description="ury 000">ury 000</SCANLINE>

    <SCANLINE hits="71" mnemonic="LKL" description="ury 100">ury 100</SCANLINE>

    <SCANLINE hits="44" mnemonic="LKL" description="ury 220">ury 220</SCANLINE>

    <SCANLINE hits="26" mnemonic="LKL" description="ury 230">ury 230</SCANLINE>

    <SCANLINE hits="5" mnemonic="LKL" description="ury 240">ury 240</SCANLINE>

    <SCANLINE hits="25" mnemonic="LKL" description="ury 241">ury 241</SCANLINE>

    <SCANLINE hits="32" mnemonic="LKL" description="ury 242">ury 242</SCANLINE>

    <SCANLINE hits="30" mnemonic="LKL" description="ury 250">ury 250</SCANLINE>

    <SCANLINE hits="24" mnemonic="LKL" description="ury 260">ury 260</SCANLINE>

    <SCANLINE hits="56" mnemonic="LKL" description="ury 270">ury 270</SCANLINE>

    <SCANLINE hits="67" mnemonic="LKL" description="ury 400">ury 400</SCANLINE>

    <SCANLINE hits="15" mnemonic="LKL" description="ury 460">ury 460</SCANLINE>

    <SCANLINE hits="10" mnemonic="LKL" description="ury 500">ury 500</SCANLINE>

    <SCANLINE hits="1" mnemonic="LKL" description="ury 520">ury 520</SCANLINE>

    <SCANLINE hits="2" mnemonic="LKL" description="ury 522">ury 522</SCANLINE>

    <SCANLINE hits="20" mnemonic="LKL" description="ury 524">ury 524</SCANLINE>

    <SCANLINE hits="3" mnemonic="LKL" description="ury 540">ury 540</SCANLINE>

    <SCANLINE hits="2" mnemonic="LKL" description="ury 542">ury 542</SCANLINE>

    <SCANLINE hits="10" mnemonic="LKL" description="ury 543">ury 543</SCANLINE>

    <SCANLINE hits="20" mnemonic="LKL" description="ury 544">ury 544</SCANLINE>

    <SCANLINE hits="7" mnemonic="LKL" description="ury 545">ury 545</SCANLINE>

    <SCANLINE hits="22" mnemonic="LKL" description="ury 546">ury 546</SCANLINE>

    <SCANLINE hits="2" mnemonic="LKL" description="ury 547">ury 547</SCANLINE>

    <SCANLINE hits="3" mnemonic="LKL" description="ury 560">ury 560</SCANLINE>

    <SCANLINE hits="7" mnemonic="LKL" description="ury 562">ury 562</SCANLINE>

    <SCANLINE hits="4" mnemonic="LKL" description="ury 580">ury 580</SCANLINE>

    <SCANLINE hits="9" mnemonic="LKL" description="ury 581">ury 581</SCANLINE>

    <SCANLINE hits="4" mnemonic="LKL" description="ury 582">ury 582</SCANLINE>

    <SCANLINE hits="33" mnemonic="LKL" description="ury 583">ury 583</SCANLINE>

    <SCANLINE hits="7" mnemonic="LKL" description="ury 585">ury 585</SCANLINE>

    <SCANLINE hits="3" mnemonic="LKL" description="ury 586">ury 586</SCANLINE>

    <SCANLINE hits="2" mnemonic="LKL" description="ury 587">ury 587</SCANLINE>

    <SCANLINE hits="6" mnemonic="LKL" description="ury 588">ury 588</SCANLINE>

    <SCANLINE hits="8" mnemonic="LKL" description="urz 100">urz 100</SCANLINE>

    <SCANLINE hits="21" mnemonic="LKL" description="urz 200">urz 200</SCANLINE>

    <SCANLINE hits="43" mnemonic="LKL" description="urz 320">urz 320</SCANLINE>

    <SCANLINE hits="14" mnemonic="LKL" description="urz 340">urz 340</SCANLINE>

    <SCANLINE hits="17" mnemonic="LKL" description="urz 360">urz 360</SCANLINE>

    <SCANLINE hits="173" mnemonic="LKL" description="urz 400">urz 400</SCANLINE>

    <SCANLINE hits="52" mnemonic="LKL" description="urz 500">urz 500</SCANLINE>

    <SCANLINE hits="1" mnemonic="LKL" description="urz 530">urz 530</SCANLINE>

    <SCANLINE hits="163" mnemonic="LKL" description="urz 600">urz 600</SCANLINE>

    <SCANLINE hits="59" mnemonic="LKL" description="urz 710">urz 710</SCANLINE>

    <SCANLINE hits="31" mnemonic="LKL" description="urz 720">urz 720</SCANLINE>

    <SCANLINE hits="47" mnemonic="LKL" description="urz 730">urz 730</SCANLINE>

    <SCANLINE hits="31" mnemonic="LKL" description="urz 740">urz 740</SCANLINE>

    <SCANLINE hits="36" mnemonic="LKL" description="urz 750">urz 750</SCANLINE>

    <SCANLINE hits="28" mnemonic="LKL" description="urz 760">urz 760</SCANLINE>

    <SCANLINE hits="36" mnemonic="LKL" description="urz 770">urz 770</SCANLINE>

    <SCANLINE hits="35" mnemonic="LKL" description="urz 800">urz 800</SCANLINE>

    <SCANLINE hits="123" mnemonic="LKL" description="urz 850">urz 850</SCANLINE>

    <SCANLINE hits="5" mnemonic="LKL" description="urz 900">urz 900</SCANLINE>

    <SCANLINE hits="31" mnemonic="LKL" description="urz 910">urz 910</SCANLINE>

    <SCANLINE hits="2" mnemonic="LKL" description="urz 912">urz 912</SCANLINE>

    <SCANLINE hits="8" mnemonic="LKL" description="urz 920">urz 920</SCANLINE>

    <SCANLINE hits="3" mnemonic="LKL" description="urz 922">urz 922</SCANLINE>

    <SCANLINE hits="10" mnemonic="LKL" description="urz 924">urz 924</SCANLINE>

    <SCANLINE hits="15" mnemonic="LKL" description="urz 926">urz 926</SCANLINE>

    <SCANLINE hits="56" mnemonic="LKL" description="urz 928">urz 928</SCANLINE>

    <SCANLINE hits="14" mnemonic="LKL" description="urz 930">urz 930</SCANLINE>

    <SCANLINE hits="13" mnemonic="LKL" description="urz 932">urz 932</SCANLINE>

    <SCANLINE hits="2" mnemonic="LKL" description="urz 934">urz 934</SCANLINE>

    <SCANLINE hits="4" mnemonic="LKL" description="urz 936">urz 936</SCANLINE>

    <SCANLINE hits="47" mnemonic="LKL" description="urz 950">urz 950</SCANLINE>

    <SCANLINE hits="1" mnemonic="LKL" description="us hs">us hs</SCANLINE>

    <SCANLINE hits="1" mnemonic="LKL" description="us ld">us ld</SCANLINE>

    <SCANLINE hits="15" mnemonic="LKL" description="ut">ut</SCANLINE>

    <SCANLINE hits="45" mnemonic="LKL" description="ut 000">ut 000</SCANLINE>

    <SCANLINE hits="1" mnemonic="LKL" description="ut 06 finn">ut 06 finn</SCANLINE>

    <SCANLINE hits="1" mnemonic="LKL" description="ut 66 usa">ut 66 usa</SCANLINE>

    <SCANLINE hits="11" mnemonic="LKL" description="ut ab">ut ab</SCANLINE>

    <SCANLINE hits="47" mnemonic="LKL" description="ut c">ut c</SCANLINE>

    <SCANLINE hits="2" mnemonic="LKL" description="ut ca">ut ca</SCANLINE>

    <SCANLINE hits="2" mnemonic="LKL" description="ut cc">ut cc</SCANLINE>

    <SCANLINE hits="8" mnemonic="LKL" description="ut go">ut go</SCANLINE>

    <SCANLINE hits="3" mnemonic="LKL" description="ut gs">ut gs</SCANLINE>

    <SCANLINE hits="1" mnemonic="LKL" description="ut gx">ut gx</SCANLINE>

    <SCANLINE hits="1" mnemonic="LKL" description="ut hd">ut hd</SCANLINE>

    <SCANLINE hits="5" mnemonic="LKL" description="ut hs">ut hs</SCANLINE>

    <SCANLINE hits="1" mnemonic="LKL" description="ut i (fh)">ut i (fh)</SCANLINE>

    <SCANLINE hits="6" mnemonic="LKL" description="ut jf">ut jf</SCANLINE>

    <SCANLINE hits="1" mnemonic="LKL" description="ut jf a">ut jf a</SCANLINE>

    <SCANLINE hits="16" mnemonic="LKL" description="ut jk">ut jk</SCANLINE>

    <SCANLINE hits="1" mnemonic="LKL" description="ut jm">ut jm</SCANLINE>

    <SCANLINE hits="5" mnemonic="LKL" description="ut js">ut js</SCANLINE>

    <SCANLINE hits="1" mnemonic="LKL" description="ut kd">ut kd</SCANLINE>

    <SCANLINE hits="4" mnemonic="LKL" description="ut kf">ut kf</SCANLINE>

    <SCANLINE hits="5" mnemonic="LKL" description="ut kk">ut kk</SCANLINE>

    <SCANLINE hits="6" mnemonic="LKL" description="ut ld">ut ld</SCANLINE>

    <SCANLINE hits="4" mnemonic="LKL" description="ut lg">ut lg</SCANLINE>

    <SCANLINE hits="2" mnemonic="LKL" description="ut ly">ut ly</SCANLINE>

    <SCANLINE hits="1" mnemonic="LKL" description="ut m (fh)">ut m (fh)</SCANLINE>

    <SCANLINE hits="1" mnemonic="LKL" description="ut mh">ut mh</SCANLINE>

    <SCANLINE hits="1" mnemonic="LKL" description="ut mo">ut mo</SCANLINE>

    <SCANLINE hits="2" mnemonic="LKL" description="ut ng">ut ng</SCANLINE>

    <SCANLINE hits="2" mnemonic="LKL" description="ut os">ut os</SCANLINE>

    <SCANLINE hits="1" mnemonic="LKL" description="ut ou">ut ou</SCANLINE>

    <SCANLINE hits="1" mnemonic="LKL" description="ut p (fh)">ut p (fh)</SCANLINE>

    <SCANLINE hits="1" mnemonic="LKL" description="ut qll">ut qll</SCANLINE>

    <SCANLINE hits="1" mnemonic="LKL" description="ut qx">ut qx</SCANLINE>

    <SCANLINE hits="10" mnemonic="LKL" description="ut rr">ut rr</SCANLINE>

    <SCANLINE hits="33" mnemonic="LKL" description="ut ru">ut ru</SCANLINE>

    <SCANLINE hits="1" mnemonic="LKL" description="ut rv">ut rv</SCANLINE>

    <SCANLINE hits="2" mnemonic="LKL" description="ut uc">ut uc</SCANLINE>

    <SCANLINE hits="1" mnemonic="LKL" description="ut vm">ut vm</SCANLINE>

    <SCANLINE hits="9" mnemonic="LKL" description="uta 000">uta 000</SCANLINE>

    <SCANLINE hits="11" mnemonic="LKL" description="uta 100">uta 100</SCANLINE>

    <SCANLINE hits="30" mnemonic="LKL" description="uta 100 a">uta 100 a</SCANLINE>

    <SCANLINE hits="48" mnemonic="LKL" description="uta 100 k">uta 100 k</SCANLINE>

    <SCANLINE hits="69" mnemonic="LKL" description="uta 300">uta 300</SCANLINE>

    <SCANLINE hits="17" mnemonic="LKL" description="uta 300 k">uta 300 k</SCANLINE>

    <SCANLINE hits="1" mnemonic="LKL" description="uta 300 m">uta 300 m</SCANLINE>

    <SCANLINE hits="102" mnemonic="LKL" description="uta 500">uta 500</SCANLINE>

    <SCANLINE hits="22" mnemonic="LKL" description="uta 700">uta 700</SCANLINE>

    <SCANLINE hits="68" mnemonic="LKL" description="utb 000">utb 000</SCANLINE>

    <SCANLINE hits="3" mnemonic="LKL" description="utb m (fh)">utb m (fh)</SCANLINE>

    <SCANLINE hits="3" mnemonic="LKL" description="uu">uu</SCANLINE>

    <SCANLINE hits="56" mnemonic="LKL" description="uu 000">uu 000</SCANLINE>

    <SCANLINE hits="34" mnemonic="LKL" description="uu 500">uu 500</SCANLINE>

    <SCANLINE hits="37" mnemonic="LKL" description="uu 600">uu 600</SCANLINE>

    <SCANLINE hits="1" mnemonic="LKL" description="uu b (fh)">uu b (fh)</SCANLINE>

    <SCANLINE hits="3" mnemonic="LKL" description="uu hd">uu hd</SCANLINE>

    <SCANLINE hits="1" mnemonic="LKL" description="uu i (fh)">uu i (fh)</SCANLINE>

    <SCANLINE hits="2" mnemonic="LKL" description="uu k (fh)">uu k (fh)</SCANLINE>

    <SCANLINE hits="1" mnemonic="LKL" description="uu kk">uu kk</SCANLINE>

    <SCANLINE hits="1" mnemonic="LKL" description="uu ld">uu ld</SCANLINE>

    <SCANLINE hits="1" mnemonic="LKL" description="uu p">uu p</SCANLINE>

    <SCANLINE hits="1" mnemonic="LKL" description="uu q (fh)">uu q (fh)</SCANLINE>

    <SCANLINE hits="1" mnemonic="LKL" description="uu y (fh)">uu y (fh)</SCANLINE>

    <SCANLINE hits="11" mnemonic="LKL" description="uua 000">uua 000</SCANLINE>

    <SCANLINE hits="1" mnemonic="LKL" description="uua a (fh)">uua a (fh)</SCANLINE>

    <SCANLINE hits="2" mnemonic="LKL" description="uua k (fh)">uua k (fh)</SCANLINE>

    <SCANLINE hits="3" mnemonic="LKL" description="uua m (fh)">uua m (fh)</SCANLINE>

    <SCANLINE hits="1" mnemonic="LKL" description="uua n (fh)">uua n (fh)</SCANLINE>

    <SCANLINE hits="3" mnemonic="LKL" description="uub">uub</SCANLINE>

    <SCANLINE hits="99" mnemonic="LKL" description="uub 000">uub 000</SCANLINE>

    <SCANLINE hits="16" mnemonic="LKL" description="uub 100">uub 100</SCANLINE>

    <SCANLINE hits="34" mnemonic="LKL" description="uub 200">uub 200</SCANLINE>

    <SCANLINE hits="90" mnemonic="LKL" description="uub 300">uub 300</SCANLINE>

    <SCANLINE hits="38" mnemonic="LKL" description="uub 303">uub 303</SCANLINE>

    <SCANLINE hits="26" mnemonic="LKL" description="uub 306">uub 306</SCANLINE>

    <SCANLINE hits="13" mnemonic="LKL" description="uub 310">uub 310</SCANLINE>

    <SCANLINE hits="80" mnemonic="LKL" description="uub 311">uub 311</SCANLINE>

    <SCANLINE hits="109" mnemonic="LKL" description="uub 312">uub 312</SCANLINE>

    <SCANLINE hits="21" mnemonic="LKL" description="uub 313">uub 313</SCANLINE>

    <SCANLINE hits="54" mnemonic="LKL" description="uub 314">uub 314</SCANLINE>

    <SCANLINE hits="36" mnemonic="LKL" description="uub 315">uub 315</SCANLINE>

    <SCANLINE hits="40" mnemonic="LKL" description="uub 316">uub 316</SCANLINE>

    <SCANLINE hits="46" mnemonic="LKL" description="uub 320">uub 320</SCANLINE>

    <SCANLINE hits="19" mnemonic="LKL" description="uub 330">uub 330</SCANLINE>

    <SCANLINE hits="98" mnemonic="LKL" description="uub 340">uub 340</SCANLINE>

    <SCANLINE hits="17" mnemonic="LKL" description="uub 350">uub 350</SCANLINE>

    <SCANLINE hits="2" mnemonic="LKL" description="uub 360">uub 360</SCANLINE>

    <SCANLINE hits="2" mnemonic="LKL" description="uub 390">uub 390</SCANLINE>

    <SCANLINE hits="1" mnemonic="LKL" description="uub a (fh)">uub a (fh)</SCANLINE>

    <SCANLINE hits="1" mnemonic="LKL" description="uub b (fh)">uub b (fh)</SCANLINE>

    <SCANLINE hits="2" mnemonic="LKL" description="uub k (fh)">uub k (fh)</SCANLINE>

    <SCANLINE hits="4" mnemonic="LKL" description="uub m (fh)">uub m (fh)</SCANLINE>

    <SCANLINE hits="1" mnemonic="LKL" description="uub u (fh)">uub u (fh)</SCANLINE>

    <SCANLINE hits="1" mnemonic="LKL" description="uub v (fh)">uub v (fh)</SCANLINE>

    <SCANLINE hits="1" mnemonic="LKL" description="uube 300">uube 300</SCANLINE>

    <SCANLINE hits="8" mnemonic="LKL" description="uuc 000">uuc 000</SCANLINE>

    <SCANLINE hits="2" mnemonic="LKL" description="uuc 100">uuc 100</SCANLINE>

    <SCANLINE hits="3" mnemonic="LKL" description="uuc 300">uuc 300</SCANLINE>

    <SCANLINE hits="17" mnemonic="LKL" description="uud 000">uud 000</SCANLINE>

    <SCANLINE hits="1" mnemonic="LKL" description="uud k (fh)">uud k (fh)</SCANLINE>

    <SCANLINE hits="4" mnemonic="LKL" description="uud m (fh)">uud m (fh)</SCANLINE>

    <SCANLINE hits="19" mnemonic="LKL" description="uue 000">uue 000</SCANLINE>

    <SCANLINE hits="5" mnemonic="LKL" description="uue 100">uue 100</SCANLINE>

    <SCANLINE hits="15" mnemonic="LKL" description="uue 200">uue 200</SCANLINE>

    <SCANLINE hits="10" mnemonic="LKL" description="uue 300">uue 300</SCANLINE>

    <SCANLINE hits="10" mnemonic="LKL" description="uue 400">uue 400</SCANLINE>

    <SCANLINE hits="22" mnemonic="LKL" description="uue 600">uue 600</SCANLINE>

    <SCANLINE hits="6" mnemonic="LKL" description="uue 700">uue 700</SCANLINE>

    <SCANLINE hits="1" mnemonic="LKL" description="uue i (fh)">uue i (fh)</SCANLINE>

    <SCANLINE hits="2" mnemonic="LKL" description="uue k (fh)">uue k (fh)</SCANLINE>

    <SCANLINE hits="3" mnemonic="LKL" description="uue m (fh)">uue m (fh)</SCANLINE>

    <SCANLINE hits="2" mnemonic="LKL" description="uuf 000">uuf 000</SCANLINE>

    <SCANLINE hits="2" mnemonic="LKL" description="uuf 100">uuf 100</SCANLINE>

    <SCANLINE hits="2" mnemonic="LKL" description="uuf 400">uuf 400</SCANLINE>

    <SCANLINE hits="1" mnemonic="LKL" description="uuf q (fh)">uuf q (fh)</SCANLINE>

    <SCANLINE hits="1" mnemonic="LKL" description="uug">uug</SCANLINE>

    <SCANLINE hits="90" mnemonic="LKL" description="uuh 000">uuh 000</SCANLINE>

    <SCANLINE hits="6" mnemonic="LKL" description="uuh 100">uuh 100</SCANLINE>

    <SCANLINE hits="6" mnemonic="LKL" description="uuh 300">uuh 300</SCANLINE>

    <SCANLINE hits="2" mnemonic="LKL" description="uuh 500">uuh 500</SCANLINE>

    <SCANLINE hits="1" mnemonic="LKL" description="uuh a (fh)">uuh a (fh)</SCANLINE>

    <SCANLINE hits="1" mnemonic="LKL" description="uuh d (fh)">uuh d (fh)</SCANLINE>

    <SCANLINE hits="3" mnemonic="LKL" description="uuh i (fh)">uuh i (fh)</SCANLINE>

    <SCANLINE hits="1" mnemonic="LKL" description="uuh l (fh)">uuh l (fh)</SCANLINE>

    <SCANLINE hits="2" mnemonic="LKL" description="uui 000">uui 000</SCANLINE>

    <SCANLINE hits="28" mnemonic="LKL" description="uuk 000">uuk 000</SCANLINE>

    <SCANLINE hits="4" mnemonic="LKL" description="uuk i (fh)">uuk i (fh)</SCANLINE>

    <SCANLINE hits="1" mnemonic="LKL" description="uuk m (fh)">uuk m (fh)</SCANLINE>

    <SCANLINE hits="1" mnemonic="LKL" description="uuk uu">uuk uu</SCANLINE>

    <SCANLINE hits="1" mnemonic="LKL" description="uv">uv</SCANLINE>

    <SCANLINE hits="1" mnemonic="LKL" description="uv 2 c 2">uv 2 c 2</SCANLINE>

    <SCANLINE hits="6" mnemonic="LKL" description="uw 000">uw 000</SCANLINE>

    <SCANLINE hits="1" mnemonic="LKL" description="uw go">uw go</SCANLINE>

    <SCANLINE hits="13" mnemonic="LKL" description="uwa 000">uwa 000</SCANLINE>

    <SCANLINE hits="3" mnemonic="LKL" description="uwa 100">uwa 100</SCANLINE>

    <SCANLINE hits="3" mnemonic="LKL" description="uwa 200">uwa 200</SCANLINE>

    <SCANLINE hits="5" mnemonic="LKL" description="uwa 300">uwa 300</SCANLINE>

    <SCANLINE hits="5" mnemonic="LKL" description="uwa 400">uwa 400</SCANLINE>

    <SCANLINE hits="10" mnemonic="LKL" description="uwa 500">uwa 500</SCANLINE>

    <SCANLINE hits="20" mnemonic="LKL" description="uwe 000">uwe 000</SCANLINE>

    <SCANLINE hits="7" mnemonic="LKL" description="uwe 050">uwe 050</SCANLINE>

    <SCANLINE hits="63" mnemonic="LKL" description="uwe 100">uwe 100</SCANLINE>

    <SCANLINE hits="4" mnemonic="LKL" description="uwe 200">uwe 200</SCANLINE>

    <SCANLINE hits="6" mnemonic="LKL" description="uwe 300">uwe 300</SCANLINE>

    <SCANLINE hits="8" mnemonic="LKL" description="uwe 400">uwe 400</SCANLINE>

    <SCANLINE hits="3" mnemonic="LKL" description="uwe 500">uwe 500</SCANLINE>

    <SCANLINE hits="5" mnemonic="LKL" description="uwe 600">uwe 600</SCANLINE>

    <SCANLINE hits="2" mnemonic="LKL" description="uwe 700">uwe 700</SCANLINE>

    <SCANLINE hits="1" mnemonic="LKL" description="uwe d (fh)">uwe d (fh)</SCANLINE>

    <SCANLINE hits="2" mnemonic="LKL" description="uwe k (fh)">uwe k (fh)</SCANLINE>

    <SCANLINE hits="24" mnemonic="LKL" description="uwk 000">uwk 000</SCANLINE>

    <SCANLINE hits="1" mnemonic="LKL" description="uwk v (fh)">uwk v (fh)</SCANLINE>

    <SCANLINE hits="38" mnemonic="LKL" description="uwl 000">uwl 000</SCANLINE>

    <SCANLINE hits="1" mnemonic="LKL" description="uwl a (fh)">uwl a (fh)</SCANLINE>

    <SCANLINE hits="1" mnemonic="LKL" description="uwl v (fh)">uwl v (fh)</SCANLINE>

    <SCANLINE hits="15" mnemonic="LKL" description="ux">ux</SCANLINE>

    <SCANLINE hits="3" mnemonic="LKL" description="uy">uy</SCANLINE>

    <SCANLINE hits="2" mnemonic="LKL" description="uy 000">uy 000</SCANLINE>

    <SCANLINE hits="1" mnemonic="LKL" description="uy 100">uy 100</SCANLINE>

    <SCANLINE hits="1" mnemonic="LKL" description="uy ru">uy ru</SCANLINE>

    <SCANLINE hits="6" mnemonic="LKL" description="uy tw">uy tw</SCANLINE>

    <SCANLINE hits="3" mnemonic="LKL" description="uya 000">uya 000</SCANLINE>

    <SCANLINE hits="2" mnemonic="LKL" description="uya 100">uya 100</SCANLINE>

    <SCANLINE hits="1" mnemonic="LKL" description="uya10 e a (fh)">uya10 e a (fh)</SCANLINE>

    <SCANLINE hits="4" mnemonic="LKL" description="uyb 000">uyb 000</SCANLINE>

    <SCANLINE hits="19" mnemonic="LKL" description="uyb 100">uyb 100</SCANLINE>

    <SCANLINE hits="16" mnemonic="LKL" description="uyb 200">uyb 200</SCANLINE>

    <SCANLINE hits="2" mnemonic="LKL" description="uyb 400">uyb 400</SCANLINE>

    <SCANLINE hits="11" mnemonic="LKL" description="uyb 600">uyb 600</SCANLINE>

    <SCANLINE hits="1" mnemonic="LKL" description="uyb11 me v (fh)">uyb11 me v (fh)</SCANLINE>

    <SCANLINE hits="1" mnemonic="LKL" description="uyb16 oe k (fh)">uyb16 oe k (fh)</SCANLINE>

    <SCANLINE hits="1" mnemonic="LKL" description="uyb16 oe m (fh)">uyb16 oe m (fh)</SCANLINE>

    <SCANLINE hits="2" mnemonic="LKL" description="uyb20 d a (fh)">uyb20 d a (fh)</SCANLINE>

    <SCANLINE hits="7" mnemonic="LKL" description="uyc 000">uyc 000</SCANLINE>

    <SCANLINE hits="3" mnemonic="LKL" description="uyd 000">uyd 000</SCANLINE>

    <SCANLINE hits="2" mnemonic="LKL" description="uyd16 gb a">uyd16 gb a</SCANLINE>

    <SCANLINE hits="3" mnemonic="LKL" description="uyd16 gb a (fh)">uyd16 gb a (fh)</SCANLINE>

    <SCANLINE hits="1" mnemonic="LKL" description="uyd16 gb v (fh)">uyd16 gb v (fh)</SCANLINE>

    <SCANLINE hits="1" mnemonic="LKL" description="uyd16 po k (fh)">uyd16 po k (fh)</SCANLINE>

    <SCANLINE hits="12" mnemonic="LKL" description="uye 000">uye 000</SCANLINE>

    <SCANLINE hits="1" mnemonic="LKL" description="uye16 it a (fh)">uye16 it a (fh)</SCANLINE>

    <SCANLINE hits="1" mnemonic="LKL" description="uye16 it v (fh)">uye16 it v (fh)</SCANLINE>

    <SCANLINE hits="5" mnemonic="LKL" description="uyf 000">uyf 000</SCANLINE>

    <SCANLINE hits="4" mnemonic="LKL" description="uyg 000">uyg 000</SCANLINE>

    <SCANLINE hits="1" mnemonic="LKL" description="uyg16 po k (fh)">uyg16 po k (fh)</SCANLINE>

    <SCANLINE hits="1" mnemonic="LKL" description="uyg16 su v (fh)">uyg16 su v (fh)</SCANLINE>

    <SCANLINE hits="1" mnemonic="LKL" description="uyg16 un k (fh)">uyg16 un k (fh)</SCANLINE>

    <SCANLINE hits="1" mnemonic="LKL" description="uyw60 usa a (fh)">uyw60 usa a (fh)</SCANLINE>

    <SCANLINE hits="2" mnemonic="LKL" description="uyw66 ka a">uyw66 ka a</SCANLINE>

    <SCANLINE hits="1" mnemonic="LKL" description="uyw66 usa a (fh)">uyw66 usa a (fh)</SCANLINE>

    <SCANLINE hits="6" mnemonic="LKL" description="uyz70 au a">uyz70 au a</SCANLINE>

    <SCANLINE hits="1" mnemonic="LKL" description="uz">uz</SCANLINE>

    <SCANLINE hits="3399" mnemonic="LKL" description="v">v</SCANLINE>

    <SCANLINE hits="1" mnemonic="LKL" description="v 0">v 0</SCANLINE>

    <SCANLINE hits="449" mnemonic="LKL" description="v 000">v 000</SCANLINE>

    <SCANLINE hits="98" mnemonic="LKL" description="v 100">v 100</SCANLINE>

    <SCANLINE hits="2" mnemonic="LKL" description="v 16 belg">v 16 belg</SCANLINE>

    <SCANLINE hits="1" mnemonic="LKL" description="v 16 d">v 16 d</SCANLINE>

    <SCANLINE hits="1" mnemonic="LKL" description="v 16 daen">v 16 daen</SCANLINE>

    <SCANLINE hits="1" mnemonic="LKL" description="v 16 deutsches reich ve 16 deutsches reich">v 16 deutsches reich ve 16 deutsches reich</SCANLINE>

    <SCANLINE hits="6" mnemonic="LKL" description="v 16 frank">v 16 frank</SCANLINE>

    <SCANLINE hits="1" mnemonic="LKL" description="v 16 frank vu 16 frank">v 16 frank vu 16 frank</SCANLINE>

    <SCANLINE hits="12" mnemonic="LKL" description="v 16 gb">v 16 gb</SCANLINE>

</SCANLIST>

<SCANPREV term="uri+800" />


<SCANNEXT term="v+16+gb" />

</RESULT>
